[{"type":"Bác sỹ nha khoa","store":"Cơ Sở Dịch Vụ Trồng Răng Giả","address":"128 Phùng Khắc Khoan, P. Phú Thịnh, Sơn Tây, Hà Nội 100000, Vietnam","location":"21.1330355,105.5105417","phone":"+84 24 3361 7438","site":"...","img":""},{"type":"Bác sỹ nha khoa","store":"Phòng Khám Răng Hàm Mặt Bác Sỹ Hương","address":"Cụm 8, Thị Trấn Phúc Thọ, Huyện Phúc Thọ, Thành Phố Hà Nội, TT. Phúc Thọ, Phúc Thọ, Hà Nội 100000, Vietnam","location":"21.1071815,105.5385208","phone":"+84 98 226 12 04","site":"...","img":""},{"type":"Bác sỹ nha khoa","store":"Nha Khoa 108","address":"Cụm 8, Thị Trấn Phúc Thọ, Huyện Phúc Thọ, Thành Phố Hà Nội, TT. Phúc Thọ, Phúc Thọ, Hà Nội 100000, Vietnam","location":"21.106506,105.538147","phone":"+84 91 331 12 45","site":"...","img":""},{"type":"Bác sỹ nha khoa","store":"Phòng Khám Răng Hàm Mặt Phương Linh","address":"Tùng Thiện, Thị Xã Sơn Tây, Thành Phố Hà Nội, P. Sơn Lộc, Sơn Tây, Hà Nội 100000, Vietnam","location":"21.1122149,105.4952325","phone":"+84 98 246 36 02","site":"...","img":""},{"type":"Bác sỹ nha khoa","store":"Nha Khoa Bảo Linh","address":"Đại Đồng, Thạch Thất, Hanoi, Vietnam","location":"21.0832008,105.5640717","phone":"+84 98 678 29 96","site":"...","img":"https://lh3.googleusercontent.com/p/AF1QipPafgVajy0ipdyV-iB8c3x3mlellvFrmGkNP_JE=s1600-w400,https://lh3.googleusercontent.com/p/AF1QipN6Qs81Ip32iZBdfg7FCP5vvSbiTJ3WJ5L9yyB-=s1600-w400,"},{"type":"Bác sỹ nha khoa","store":"Nha Khoa Quốc Tế Chi Nhánh Thạch Thất","address":"Số 86 Đồng Cao, Cầu Đồng Mô, Thạch Thất, Hà Nội, Vietnam","location":"21.0593292,105.5754828","phone":"+84 869 067 890","site":"...","img":"https://lh3.googleusercontent.com/p/AF1QipPP8c0BVW7EGUl3MsUY3xGDLSf7HSprC0pA6lEf=s1600-w400,https://lh3.googleusercontent.com/p/AF1QipP0IfHutMRLDDFkRVZzILDlQHtrOFmAR9-vAJzL=s1600-w400,https://lh3.googleusercontent.com/p/AF1QipNiVPMD76-I4eRz5spUXcoMyf3drkjIYnR8dh7_=s1600-w400,"},{"type":"Bác sỹ nha khoa","store":"Cơ Sở Trồng Răng Hải Vân","address":"Thị Trấn Liên Quan, Huyện Thạch Thất, Thành Phố Hà Nội, TT. Liên Quan, Thạch Thất, Hà Nội 100000, Vietnam","location":"21.0580387,105.573822","phone":"+84 91 325 37 73","site":"...","img":""},{"type":"Bác sỹ nha khoa","store":"2 ngõ 9 Tùng thiện Sơn lộc Sơn tây","address":"2, 9 Tùng Thiện, Tông, Sơn Tây, Hà Nội, Vietnam","location":"21.1129654,105.4955762","phone":"...","site":"...","img":"https://lh3.googleusercontent.com/p/AF1QipNCxzKCRKWgUvANTwJxxYdFwGcgFn4C4zBTNK2h=s1600-w400,https://lh3.googleusercontent.com/p/AF1QipPcsyQqDi9x8EXIUu4V3BNk6Plq7cixehq0sV3R=s1600-w400,https://lh3.googleusercontent.com/p/AF1QipOK0EhwiGmcHvpONmgmDFZbAPWVEp3g6LvNcUnT=s1600-w400,https://lh3.googleusercontent.com/p/AF1QipNM6xOlYCKojcLC6fesqgzezTwbEP6fMWmA6Ni_=s1600-w400,https://lh3.googleusercontent.com/p/AF1QipOKoQi-xlGPmgAMnH_rGbE0ncjrrrKaLLoxyWhI=s1600-w400,https://lh3.googleusercontent.com/p/AF1QipP8vUzid6Ua-PV09JdbnRGC4tKe1bQlsetYSLok=s1600-w400,"},{"type":"Bác sỹ nha khoa","store":"Nha Khoa Mạnh Chiến","address":"Thôn Đông Viên, Xã Đông Quang, Huyện Ba Vì, Thành Phố Hà Nội, Đồng Quang, Ba Vì, Hà Nội 100000, Vietnam","location":"21.1744898,105.4523218","phone":"+84 96 434 39 89","site":"...","img":""},{"type":"Bác sỹ nha khoa","store":"Phòng Khám Răng Hàm Mặt","address":"Thị Trấn Phúc Thọ, Huyện Phúc Thọ, Thành Phố Hà Nội, TT. Phúc Thọ, Phúc Thọ, Hà Nội 100000, Vietnam","location":"21.1059971,105.5409164","phone":"+84 91 685 15 55","site":"...","img":""},{"type":"Bác sỹ nha khoa","store":"Nha Khoa Thái Lâm","address":"449 Phố Mới, Chú Minh, Ba Vì, Hà Nội 154732, Vietnam","location":"21.1905998,105.434568","phone":"+84 94 345 13 57","site":"https://nha-khoa-thai-lam.business.site/?utm_source=gmb&utm_med","img":"https://lh3.googleusercontent.com/p/AF1QipP7oqs4eSFZOUvaqxg4Co36iPcHX47xeTZyaz5H=s1600-w400,"},{"type":"Bác sỹ nha khoa","store":"Nha Khoa Anh Phái","address":"Chùa Thông, P. Phú Thịnh, Sơn Tây, Hà Nội 100000, Vietnam","location":"21.1253414,105.5017166","phone":"+84 24 6327 7079","site":"...","img":"https://lh3.googleusercontent.com/p/AF1QipOblh_Wq0w8vlzQfkmpOZoNQkt3-1uGFjQKCLO3=s1600-w400,https://lh3.googleusercontent.com/p/AF1QipM8oCL42orv4VclaXpeN-v2cnOf7KRxt3M-2Rbv=s1600-w400,"},{"type":"Bác sỹ nha khoa","store":"Phòng Khám Nha Khoa Răng Xinh Hà Nội","address":"79, Quốc Lộ 2C, Thôn Hoàng Xá, Xã Vĩnh Thịnh, Huyện Vĩnh Tường, Tỉnh Vĩnh Phúc, Vĩnh Thịnh, Vĩnh Tường, Vĩnh Phúc, Vietnam","location":"21.1881512,105.4922418","phone":"+84 348 297 907","site":"...","img":""},{"type":"Bác sỹ nha khoa","store":"NHA KHOA TUẤN ANH 108","address":"A4, BT3, Khu Đô Thị Phú Hà, Sơn Tây, Hà Nội, Vietnam","location":"21.1487333,105.503183","phone":"+84 24 3395 9933","site":"...","img":"https://lh3.googleusercontent.com/p/AF1QipMh6EbSK98WUhvbBGPw4YT2FXzBBpsQCQX-xsGT=s1600-w400,https://lh3.googleusercontent.com/p/AF1QipOy_-rGiTHi7YHVi-kN3ZXvocV7zgPiLVak3iyN=s1600-w400,https://lh3.googleusercontent.com/p/AF1QipPGuLROm0yltoGr8dNDJFMXXfErrehZae2S4VbN=s1600-w400,https://lh3.googleusercontent.com/p/AF1QipNo9bSGCTdUJnY4xgylZJZ44opXlIvS714FR4WK=s1600-w400,https://lh3.googleusercontent.com/p/AF1QipPkveEEIAXqUitxIshwnIWUjPf1H3dFTUuFTH-q=s1600-w400,https://lh3.googleusercontent.com/p/AF1QipN6c9ZGxwbzxZtunqbzsp9EX_y-dgHsrCE8eA0_=s1600-w400,"},{"type":"Bác sỹ nha khoa","store":"Phòng Khám Răng Hàm Mặt Khánh Hà","address":"Quảng Oai, Thị Trấn Tây Đằng, Huyện Ba Vì, Thành Phố Hà Nội, TT. Tây Đằng, Ba Vì, Hà Nội 100000, Vietnam","location":"21.1987653,105.4236488","phone":"+84 98 655 63 88","site":"...","img":""},{"type":"Bác sỹ nha khoa","store":"TU'S Dental Clinic","address":"176 Định Công, Phương Liệt, Thanh Xuân, Hà Nội, Vietnam","location":"20.9833814,105.8357352","phone":"+84 97 468 37 05","site":"...","img":""},{"type":"Bác sỹ nha khoa","store":"Phòng Răng Tâm Binh","address":"Đường 916, Cổ Đông, Sơn Tây, Hà Nội 100000, Vietnam","location":"21.0463001,105.5048208","phone":"+84 97 204 49 56","site":"https://phong-rang-tam-binh.business.site/?utm_source=gmb&utm_m","img":""},{"type":"Bác sỹ nha khoa","store":"Nha Khoa Quốc Tế Việt Mỹ","address":"199 Chùa Thông, P. Phú Thịnh, Sơn Tây, Hà Nội, Vietnam","location":"21.1226285,105.5001071","phone":"+84 24 3376 6699","site":"...","img":"https://lh3.googleusercontent.com/p/AF1QipP53BXxki5M3tKO5ucBYMQ37d9ZDTVz8CrK1-qZ=s1600-w400,https://lh3.googleusercontent.com/p/AF1QipMngvgQ0TcnyoaBKlZ4WWB5eRHDFNVdqiYxajT6=s1600-w400,https://lh3.googleusercontent.com/p/AF1QipPxUMoac__8C2GDX6oyeBxJrHrrD_YAs2Cf6xiG=s1600-w400,https://lh3.googleusercontent.com/p/AF1QipPkEzBh79bfiTpp2M6HwHRnBv-3ehkWL0VN4R-T=s1600-w400,https://lh3.googleusercontent.com/p/AF1QipO2gKORT6oEcgyfiFsIy9qbUM0y73ZubXVs6CqX=s1600-w400,"},{"type":"Bác sỹ nha khoa","store":"Nha Khoa Thịnh Tú","address":"64 Phú Mỹ, TT. Tây Đằng, Ba Vì, Hà Nội 100000, Vietnam","location":"21.200087,105.424606","phone":"+84 96 118 42 92","site":"...","img":""},{"type":"Bác sỹ nha khoa","store":"Nha Khoa Thái Lâm","address":"Unnamed Road, Yên Bài, Ba Vì, Hà Nội, Vietnam","location":"21.0470757,105.4407256","phone":"...","site":"...","img":""},{"type":"Bác sỹ nha khoa","store":"Nha Khoa Thành","address":"số 1, 328 Lê Trọng Tấn, Định Công, Thanh Xuân, Hà Nội, Vietnam","location":"20.9871834,105.8354825","phone":"+84 91 586 86 55","site":"...","img":"https://lh3.googleusercontent.com/p/AF1QipP8C-pC-moS_2MgMLbaRD_1nPDZtJ8b6E4NrRfD=s1600-w400,https://lh3.googleusercontent.com/p/AF1QipMyEDfXjDa6hSWVl7lVDU5BkqKqO2THZXbnTFjL=s1600-w400,https://lh3.googleusercontent.com/p/AF1QipMnUayunQ_nw6r-zg_64pbTZ3xBNvXt7jAus5z0=s1600-w400,"},{"type":"Bác sỹ nha khoa","store":"Tiến Xuân Dental Clinic","address":"Yên Bình, Thạch Thất, Hanoi, Vietnam","location":"20.9941612,105.4898157","phone":"...","site":"...","img":""},{"type":"Bác sỹ nha khoa","store":"Phòng Khám Chữa Răng","address":"155, Đường 84, Xã Kim Quan, Huyện Thạch Thất, Thành Phố Hà Nội, Kim Quan, Thạch Thất, Hà Nội 100000, Vietnam","location":"21.0503311,105.5676269","phone":"+84 91 436 80 09","site":"...","img":""},{"type":"Bác sỹ nha khoa","store":"Nha Khoa Mai Lâm","address":"Phường Trung Sơn Trầm, Thị Xã Sơn Tây, Thành Phố Hà Nội, Trung Sơn Trầm, Sơn Tây, Hà Nội 100000, Vietnam","location":"21.1108989,105.4951553","phone":"+84 98 550 94 67","site":"...","img":""},{"type":"Bác sỹ nha khoa","store":"Phòng Khám Răng Hàm Mặt","address":"Chùa Thông, Phường Sơn Lộc, Thị Xã Sơn Tây, Thành Phố Hà Nội, P. Phú Thịnh, Sơn Tây, Hà Nội 100000, Vietnam","location":"21.1295681,105.5063934","phone":"+84 98 226 32 98","site":"...","img":""},{"type":"Bác sỹ nha khoa","store":"Nha Khoa Thẩm Mỹ","address":"52 Lê Lợi, P. Quang Trung, Sơn Tây, Hà Nội 100000, Vietnam","location":"21.142326,105.505585","phone":"+84 91 480 15 44","site":"...","img":""},{"type":"Bác sỹ nha khoa","store":"Lab Phục Hình Răng Giả","address":"142 Lê Trọng Tấn, Khương Mai, Thanh Xuân, Hà Nội, Vietnam","location":"20.9962879,105.8298952","phone":"+84 91 224 80 96","site":"...","img":""},{"type":"Bác sỹ nha khoa","store":"Nha Khoa - Thẩm Mỹ Thu Hồng","address":"Đội 5, Thạch Thất, Hà Nội, Vietnam","location":"21.0224975,105.5501011","phone":"+84 359 170 207","site":"...","img":"https://lh3.googleusercontent.com/p/AF1QipPUyhVczQHNIS42D0YnUeheAvV4TmGYGuEFirt2=s1600-w400,https://lh3.googleusercontent.com/p/AF1QipMn5SnXmHMjuRhqCvl_5qDkapnejsWbHCQ2EPnq=s1600-w400,https://lh3.googleusercontent.com/p/AF1QipMQcbgHBA7eV25n0oVIIdFjqNBrCvCwwM5txVJ7=s1600-w400,https://lh3.googleusercontent.com/p/AF1QipOlzSTmpltKyhz66uweOL-yRnW5NIgilF5iYRe1=s1600-w400,https://lh3.googleusercontent.com/p/AF1QipMFNMxXe5jEYqgBiJoS10Af4BMavxQI5F1xbxha=s1600-w400,https://lh3.googleusercontent.com/p/AF1QipNvChs8BZGrFMRG1GZ4WENIfYoP1V9t7cj2rsq7=s1600-w400,https://lh3.googleusercontent.com/p/AF1QipME6g3pMP0WxJAGa9zArJP3t2dC8YbvtD9vgKiz=s1600-w400,https://lh3.googleusercontent.com/p/AF1QipMSxebQ3cvSAo9_u5619qHNVLv68LGrKRTYHRC0=s1600-w400,"},{"type":"Bác sỹ nha khoa","store":"Nha Khoa Khánh Linh","address":"24 Trần Điền, Định Công, Thanh Xuân, Hà Nội, Vietnam","location":"20.9913044,105.8319228","phone":"+84 90 225 71 79","site":"...","img":""},{"type":"Bác sỹ nha khoa","store":"Phòng Khám Nha Khoa Nha Hải","address":"108, Chùa Thông, Phường Sơn Lộc, Thị Xã Sơn Tây, Thành Phố Hà Nội, P. Phú Thịnh, Sơn Tây, Hà Nội, Vietnam","location":"21.1244768,105.5013066","phone":"+84 24 3383 1152","site":"...","img":""},{"type":"Bác sỹ nha khoa","store":"Phòng Khám Nha Khoa Huy Chuẩn Số 46 Quan Nhân, Trung Hòa, Cầu Giấy, Hà Nội.","address":"36 Quan Nhân, Trung Hoà, Cầu Giấy, Hà Nội, Vietnam","location":"21.0078364,105.8125592","phone":"+84 98 925 53 36","site":"...","img":"https://lh3.googleusercontent.com/p/AF1QipO1mISrYoZF8O5C3-a_SjRE-h2aZYBnEL4UDwd8=s1600-w400,https://lh3.googleusercontent.com/p/AF1QipMrHOO76YsSjijGqtR8JsoBIsXb4PaQkC3b2sJc=s1600-w400,"},{"type":"Bác sỹ nha khoa","store":"Nha Khoa Quốc Tế","address":"52, Phùng Khắc Khoan, P. Phú Thịnh, Sơn Tây, Hà Nội, Vietnam","location":"21.1344861,105.5091045","phone":"+84 24 3391 5999","site":"http://nhakhoaquocte.com.vn/dich-vu.html","img":"https://lh3.googleusercontent.com/p/AF1QipOwqxyWi3L6U6IBVWO3Q0XnLuFAnNJ1YQyQGE6z=s1600-w400,https://lh3.googleusercontent.com/p/AF1QipMg56flGzPd2M1yzobcWCLwNJuu8HEze0EbUo0o=s1600-w400,"},{"type":"Bác sỹ nha khoa","store":"Phòng Khám Nha Khoa Thẩm Mỹ","address":"55 Ngô Quyền, P. Ngô Quyền, Sơn Tây, Hà Nội, Vietnam","location":"21.143457,105.5001875","phone":"+84 98 387 96 77","site":"...","img":""},{"type":"Bác sỹ nha khoa","store":"Phòng Khám Răng, Hàm, Mặt","address":"86 Phùng Khắc Khoan, P. Phú Thịnh, Sơn Tây, Hà Nội, Vietnam","location":"21.1356477,105.5081692","phone":"...","site":"...","img":""},{"type":"Bác sỹ nha khoa","store":"Thành Lợi dental Lab","address":"8 Ngõ 41- Phố Đông Tác, Kim Liên, Đống Đa, Hà Nội, Vietnam","location":"21.005106,105.832899","phone":"...","site":"...","img":""},{"type":"Bác sỹ nha khoa","store":"Nha khoa Kaizen","address":"Kiôt số 10, Chung cư CT36, 326, Phố Lê Trọng Tấn, Phường Phương Mai, Quận Thanh Xuân, Định Công, Hoàng Mai, Hà Nội 100000, Vietnam","location":"20.9874706,105.8352058","phone":"+84 94 585 95 39","site":"https://kaizen-clinic.com/","img":""},{"type":"Bác sỹ nha khoa","store":"NHA KHOA THẨM MỸ QUỐC TẾ HT","address":"Tầng 2, 86 Lê Trọng Tấn, Khương Mai, Thanh Xuân, Hà Nội 100000, Vietnam","location":"20.998226,105.828782","phone":"+84 91 215 22 99","site":"http://nhakhoaht.com/","img":"https://lh3.googleusercontent.com/p/AF1QipNKzTTUHcm8J5D0oaaaxrFIX9ejLdxV-Q2iRIFj=s1600-w400,https://lh3.googleusercontent.com/p/AF1QipPPP9NSxprdO2kZQCplRBWiEScLKE-D1IPwlXRw=s1600-w400,https://lh3.googleusercontent.com/p/AF1QipMK-Z1mUXl5WKQAgWRLRwCUgHHHtC4iT8V0mjl9=s1600-w400,https://lh3.googleusercontent.com/p/AF1QipO2dh13BHYKT6CZyev8AVQ_GbGt3eNfUjjCF1__=s1600-w400,https://lh3.googleusercontent.com/p/AF1QipMOB5Iyu129hS1CD75oLecf6h7cIfsF9psKxjxm=s1600-w400,https://lh3.googleusercontent.com/p/AF1QipP0aho4Y7g0odkcBpZHaMEu-NIy72vvbMh5HNAK=s1600-w400,https://lh3.googleusercontent.com/p/AF1QipM1CeYHqhfnBPOp8ErHIqPdhWO34jRtEQy8g3k6=s1600-w400,https://lh3.googleusercontent.com/p/AF1QipO35pl9dADh94K1BMqRa32aYzx2WtJ7ajBJlzyR=s1600-w400,https://lh3.googleusercontent.com/p/AF1QipNeGN4u7fUVqjBX5DEM7PgJ3vdRTuoJSA8KFxfg=s1600-w400,https://lh3.googleusercontent.com/p/AF1QipMZ9JW7XpU4EWGFgTMdql58mO9deIRAaeSJs5zb=s1600-w400,"},{"type":"Bác sỹ nha khoa","store":"Phòng Khám Răng Hàm Mặt - Tai Mũi Họng","address":"10, Trung Tâm Thương Mại Định Công, Phường Định Công, Quận Hoàng Mai, Thành Phố Hà Nội, Định Công, Hoàng Mai, Hà Nội, Vietnam","location":"20.9852771,105.8339347","phone":"+84 24 6251 7368","site":"...","img":""},{"type":"Bác sỹ nha khoa","store":"Nha khoa Thanh Tùng","address":"81 Trần Nguyên Đán, Định Công, Hoàng Mai, Hà Nội, Vietnam","location":"20.9882714,105.8309594","phone":"+84 827 322 666","site":"http://nhakhoathanhtung.com/","img":"https://lh3.googleusercontent.com/p/AF1QipONR01V4JT-J-bULDQLab5bKJC-e3SsSKOkdYhq=s1600-w400,https://lh3.googleusercontent.com/p/AF1QipMwj4Ro0oIBsiwDZcE487nnJwNjxmZdjshPRx2k=s1600-w400,https://lh3.googleusercontent.com/p/AF1QipMr2cSxupVetaV08ehlB3jUJxnj5obawicGTbVh=s1600-w400,"},{"type":"Bác sỹ nha khoa","store":"kaizen dental clinic","address":"Kiôt số 10, Chung cư CT36, 326, Phố Lê Trọng Tấn, Định Công, Hoàng Mai, Hà Nội 10000, Vietnam","location":"20.9874698,105.8351948","phone":"+84 91 731 38 55","site":"https://kaizen-clinic.com/","img":"https://lh3.googleusercontent.com/p/AF1QipMAt4cGJVW6ze2u9KdW2cFtW5WFdzSMabNZsWi_=s1600-w400,"},{"type":"Bác sỹ nha khoa","store":"Công Ty TNHH Y Tế Thành Thịnh","address":"185A, Nguyễn Ngọc Vũ, Phường Trung Hoà, Quận Cầu Giấy, Thành Phố Hồ Chí Minh, Trung Hoà, Cầu Giấy, Hà Nội, Vietnam","location":"21.0088726,105.8125466","phone":"+84 24 6259 6688","site":"...","img":"https://lh3.googleusercontent.com/p/AF1QipOwHdq8Kfx0EbOYxQJmSiJRerw0uYTVh_d7H61H=s1600-w400,https://lh3.googleusercontent.com/p/AF1QipM4vG3-wMRYRts9IFmzQDS3HD3rTqVQFCefcSjz=s1600-w400,https://lh3.googleusercontent.com/p/AF1QipOSBFEsDlFOfRJfR0R5IPr9T9cW8705VaB8lvHI=s1600-w400,"},{"type":"Bác sỹ nha khoa","store":"Nha Khoa Quốc Tế HD","address":"73, Định Công, Quận Hoàng Mai, Thành Phố Hà Nội, Phương Liệt, Thanh Xuân, Hà Nội, Vietnam","location":"20.9835092,105.8353004","phone":"+84 98 500 77 32","site":"...","img":""},{"type":"Bác sỹ nha khoa","store":"Nha Khoa Thái Học","address":"164 Hoàng Văn Thái, Khương Trung, Thanh Xuân, Hà Nội, Vietnam","location":"20.9970513,105.8245706","phone":"+84 24 6328 5771","site":"...","img":""},{"type":"Bác sỹ nha khoa","store":"Nha khoa smile diamon","address":"30 Nguyễn Viết Xuân, Khương Mai, Thanh Xuân, Hà Nội 120700, Vietnam","location":"20.9991335,105.8277409","phone":"+84 91 237 55 00","site":"...","img":""},{"type":"Bác sỹ nha khoa","store":"PHÒNG KHÁM NHA","address":"40 Đông Tác, Kim Liên, Đống Đa, Hà Nội, Vietnam","location":"21.0058598,105.8324196","phone":"+84 98 730 26 21","site":"https://www.nhakhoaquocteachau.vn/","img":""},{"type":"Bác sỹ nha khoa","store":"Nha Khoa Hoàng Trang","address":"Unnamed Road, Long Xuyên, Phúc Thọ, Hà Nội, Vietnam","location":"21.1286836,105.5753549","phone":"+84 98 918 55 92","site":"...","img":""},{"type":"Bác sỹ nha khoa","store":"Nha Khoa Tuấn Anh 108","address":"A4 BT3, Khu Đô Thị, Sơn Tây, Hà Nội, Vietnam","location":"21.1488088,105.5031851","phone":"+84 98 907 48 56","site":"...","img":"https://lh3.googleusercontent.com/p/AF1QipMwV-qeMbRl8a7_vkMN8okwG5soJ6rICgvegu67=s1600-w400,https://lh3.googleusercontent.com/p/AF1QipN09d1xW8kNMrotUliY5z0lF6M7YOdMZFdBy27q=s1600-w400,https://lh3.googleusercontent.com/p/AF1QipNWQ1zEaBGaOa6MtXFITzNltIYJgMipWRtx50yK=s1600-w400,"},{"type":"Bác sỹ nha khoa","store":"Dr. Van Huong Hoang","address":"Số 1 Tôn Thất Tùng, Kim Liên, Đống Đa, Hà Nội 100000, Vietnam","location":"21.0035049,105.8317025","phone":"+84 333 115 115","site":"https://dr-van-huong-hoang.business.site/?utm_source=gmb&utm_me","img":"https://lh3.googleusercontent.com/p/AF1QipMeD-SVDrZddQT2HJWkbBlEbXPzuYzt5w_HN5Yq=s1600-w400,https://lh3.googleusercontent.com/p/AF1QipPhcQwQHblr31ciBNb4vQSGmsehKWZJj1Sni1wq=s1600-w400,https://lh3.googleusercontent.com/p/AF1QipMb6zqxzuaQVkwC9OGtTyHD3xiG5CCOzaAZOf3d=s1600-w400,https://lh3.googleusercontent.com/p/AF1QipM-jt360SUP2z6nR0wWejX7e-fOLqyy3vN-5fVO=s1600-w400,https://lh3.googleusercontent.com/p/AF1QipNaFRY0M6Zq4TeTIK-f2kZpsxjz1HpzhupJ3gSw=s1600-w400,"},{"type":"Bác sỹ nha khoa","store":"NHA KHOA HẢI YẾN","address":"Số 6 Chùa Thông, P. Sơn Lộc, Sơn Tây, Hà Nội, Vietnam","location":"21.1174862,105.496999","phone":"+84 97 504 80 86","site":"...","img":""},{"type":"Bác sỹ nha khoa","store":"Nha Khoa Pháp","address":"54 Hoàng Văn Thái, Khương Mai, Thanh Xuân, Hà Nội 100000, Vietnam","location":"20.996327,105.8277559","phone":"+84 98 573 39 22","site":"...","img":""},{"type":"Bác sỹ nha khoa","store":"Phòng Trồng Răng Thịnh Vượng","address":"Thôn Hưng Thịnh, Xã Đường Lâm, Thị Xã Sơn Tây, Thành Phố Hà Nội, Đường Lâm, Sơn Tây, Hà Nội 100000, Vietnam","location":"21.155687,105.478439","phone":"+84 98 876 03 88","site":"...","img":""},{"type":"Bác sỹ nha khoa","store":"Nha Khoa Dr Ha Tuyen","address":"61 Định Công, street, Hoàng Mai, Hà Nội, Vietnam","location":"20.9848149,105.8400279","phone":"...","site":"...","img":""},{"type":"Bác sỹ nha khoa","store":"HỒNG HẢI Dental","address":"12/2 Đốc Ngữ Thị xã Sơn Tây_ HN, P. Quang Trung, Sơn Tây, Hà Nội, Vietnam","location":"21.1419143,105.5071765","phone":"+84 90 403 73 35","site":"...","img":"https://lh3.googleusercontent.com/p/AF1QipOF9Kzx2C7UCSPNYnjUOsVlFEzbDxWMveFu4BGN=s1600-w400,https://lh3.googleusercontent.com/p/AF1QipOT1yPvRrRDnO3QfXISRTRWvoCHYXPor0FkeGZf=s1600-w400,https://lh3.googleusercontent.com/p/AF1QipOC31W6F5NBx6KY74ejOPsPtZcvs6P5YXAkF5jv=s1600-w400,https://lh3.googleusercontent.com/p/AF1QipNSRovafv7QUHhvtxW7L-Tz4kAR6LG0EOp_n0YJ=s1600-w400,https://lh3.googleusercontent.com/p/AF1QipOPqrRvgHyQ2lCuT44vZAkmn897UEf4g7w-ASEG=s1600-w400,"},{"type":"Bác sỹ nha khoa","store":"Huy Chuan Dental Clinic","address":"46 Quan Nhân, Trung Hoà, Cầu Giấy, Hà Nội, Vietnam","location":"21.007872,105.812291","phone":"...","site":"...","img":""},{"type":"Bác sỹ nha khoa","store":"Răng Hàm Mặt","address":"182 Vương Thừa Vũ, Khương Trung, Thanh Xuân, Hà Nội, Vietnam","location":"20.9960142,105.8218861","phone":"...","site":"...","img":""},{"type":"Bác sỹ nha khoa","store":"Nha Khoa Pha Lê","address":"Lê Trọng Tấn, Định Công, Hoàng Mai, Hà Nội, Vietnam","location":"20.985752,105.824447","phone":"+84 97 384 68 68","site":"https://nha-khoa-pha-le.business.site/?utm_source=gmb&utm_mediu","img":"https://lh3.googleusercontent.com/p/AF1QipM09fRT4B9lCPHlO3V6zEonmo-yCmiO4x8RsVgn=s1600-w400,"},{"type":"Bác sỹ nha khoa","store":"NHA KHOA HÀ NỘI","address":"137 An Trạch, Cát Linh, Đống Đa, Định Công Thượng, Hoàng Mai, Hà Nội, Vietnam","location":"20.9799344,105.8277874","phone":"+84 98 730 26 21","site":"https://www.nhakhoaquocteachau.vn/","img":""},{"type":"Bác sỹ nha khoa","store":"Nha Khoa Gia Đình Cơ Sở 1","address":"3 Nguyễn Ngọc Vũ, Trung Hoà, Cầu Giấy, Hà Nội, Vietnam","location":"21.0085754,105.8131044","phone":"+84 98 244 98 01","site":"http://nhakhoafamily.vn/","img":"https://lh3.googleusercontent.com/p/AF1QipOkfiEKJJO6wWdTSPxd3a68AbYDD8-2wEyg4NbY=s1600-w400,https://lh3.googleusercontent.com/p/AF1QipM0oOL9DUdDszYUVyrj04CMfGRLSw4DHvfCj8Cz=s1600-w400,https://lh3.googleusercontent.com/p/AF1QipNrSA7JFoV1VjktcJfTgD-7cvh4GCBqNdrUHx6C=s1600-w400,https://lh3.googleusercontent.com/p/AF1QipMui3PPmk_xroA1JTPLT4f72iUlYIGw6roztmsu=s1600-w400,https://lh3.googleusercontent.com/p/AF1QipPyLc-Ru-FcMxG-E2gNOtcgTpDfh3N-GxznVqSx=s1600-w400,https://lh3.googleusercontent.com/p/AF1QipNeuDnrMfEOEc9lMAbPBU7X6BqWFvsuFE9njFR6=s1600-w400,https://lh3.googleusercontent.com/p/AF1QipPUzjHVbscHGJmWAtboRkFciMH6fUrBwgNj2n5W=s1600-w400,https://lh3.googleusercontent.com/p/AF1QipMxAMIw1WYs5EytNqDNWuNl5bCgTZ0HyXhGBK4z=s1600-w400,https://lh3.googleusercontent.com/p/AF1QipOwD2mTYZS5WvwO9-EbCoMd815t1peU8rXjFBAk=s1600-w400,https://lh3.googleusercontent.com/p/AF1QipMdl9MeUOQ-8pYd8SskiCOvErRTwqRme2dK151P=s1600-w400,"},{"type":"Bác sỹ nha khoa","store":"Nha Khoa Hương Tân","address":"Căn 410A2, 176 Định Công, Phương Liệt, Thanh Xuân, Hà Nội 10000, Vietnam","location":"20.9833516,105.8357127","phone":"+84 94 814 78 91","site":"http://nhakhoahuongtan.com/","img":"https://lh3.googleusercontent.com/p/AF1QipN7QbfRk1TQ-x7jxuC6ZRoenTX5iq6mARaZjcu-=s1600-w400,https://lh3.googleusercontent.com/p/AF1QipPag7dDOKVVbqT9K-ozQY113oKxrNvBmLXMT-S4=s1600-w400,https://lh3.googleusercontent.com/p/AF1QipNtXdX9gs3K1eoeCei2uthCAmSRGmAGL-PMcmZB=s1600-w400,https://lh3.googleusercontent.com/p/AF1QipNwQk-vSTDFoWYl6fRRpK_THONMI5DFQhDECTIz=s1600-w400,https://lh3.googleusercontent.com/p/AF1QipOlVjJuwrsDZd-XZc7QzR_J9W2b0Tbp2_qX5O9h=s1600-w400,https://lh3.googleusercontent.com/p/AF1QipNkK-m9IsESYvONEzs_FDZ4J9jgJ1ccEDflNy6F=s1600-w400,https://lh3.googleusercontent.com/p/AF1QipMACDyNhziddtQTHxkGofvAJZvJ0CclwKQdZDcX=s1600-w400,https://lh3.googleusercontent.com/p/AF1QipP-UL6LESQULUWejzV_xSz8Xa7-LIVxid1hfH5k=s1600-w400,https://lh3.googleusercontent.com/p/AF1QipND1fL57AJbYHg2EPEa2N1dOT014uSMVP4MpmoF=s1600-w400,https://lh3.googleusercontent.com/p/AF1QipNMswA8uKeOuHjm1QVpYaZnqhCaRTkYf_iCaTMN=s1600-w400,"},{"type":"Bác sỹ nha khoa","store":"Nha Khoa Linh Anh","address":"203 Nguyễn Trãi, Thượng Đình, Thanh Xuân, Hà Nội, Vietnam","location":"20.9982807,105.8136009","phone":"+84 97 782 98 99","site":"...","img":""},{"type":"Bác sỹ nha khoa","store":"PHÒNG KHÁM RĂNG UY TÍN","address":"55 Lê Trọng Tấn, Khương Mai, Thanh Xuân, Hà Nội, Vietnam","location":"20.9919145,105.8317868","phone":"+84 98 730 26 21","site":"https://www.nhakhoaquocteachau.vn/","img":""},{"type":"Bác sỹ nha khoa","store":"Nha Khoa Trần Gia","address":"73, Ngõ 192, Lê Trọng Tấn, Phường Định Công, Quận Hoàng Mai, Thành Phố Hà Nội, Khương Mai, Thanh Xuân, Hà Nội, Vietnam","location":"20.99329,105.82946","phone":"+84 91 567 67 03","site":"...","img":""},{"type":"Bác sỹ nha khoa","store":"Nha Khoa Thẩm Mỹ","address":"164 Hoàng Văn Thái, Khương Trung, Thanh Xuân, Hà Nội 100000, Vietnam","location":"20.9969722,105.8245306","phone":"+84 91 235 59 61","site":"...","img":""},{"type":"Bác sỹ nha khoa","store":"Dinh Van Huynh Dental Clinic","address":"2CT9, Khu Đô Thị Định Công, Phường Định Công, Quận Hoàng Mai, Định Công, Hoàng Mai, Hà Nội, Vietnam","location":"20.988718,105.83126","phone":"+84 98 427 77 42","site":"...","img":""},{"type":"Bác sỹ nha khoa","store":"Nha Khoa Hạnh Phúc","address":"172 Bùi Xương Trạch, Khương Đình, Thanh Xuân, Hà Nội, Vietnam","location":"20.9886645,105.818012","phone":"...","site":"...","img":""},{"type":"Bác sỹ nha khoa","store":"Phòng khám RHM BS.Hà","address":"No.55A 228 Le Trong Tan, Định Công, Thanh Xuân, Hà Nội, Vietnam","location":"20.9907745,105.8317723","phone":"+84 24 3565 4199","site":"...","img":""},{"type":"Bác sỹ nha khoa","store":"Cam Van Dental Clinic","address":"17, Chinh Kinh Street, Thanh Xuan District, Nhân Chính, Ha Noi City, Hà Nội, Vietnam","location":"20.9996488,105.8117053","phone":"+84 91 482 82 27","site":"...","img":""},{"type":"Bác sỹ nha khoa","store":"Nha Khoa Minh Châu II","address":"455 Vũ Tông Phan, Khương Đình, Thanh Xuân, Hà Nội, Vietnam","location":"20.9874765,105.8137049","phone":"+84 96 830 74 96","site":"...","img":""},{"type":"Bác sỹ nha khoa","store":"VIỆN NIỀNG RĂNG 5 SAO HÀ NỘI","address":"444 Nguyễn Trãi, Thanh Xuân Trung, Thanh Xuân, Hà Nội, Vietnam","location":"20.992926,105.805459","phone":"+84 98 730 26 21","site":"http://nhakhoaquocteachau.vn/","img":""},{"type":"Bác sỹ nha khoa","store":"Nha Khoa Tâm Đức","address":"220 Phố Khương Trung, Khương Trung, Thanh Xuân, Hà Nội, Vietnam","location":"20.9944727,105.8173151","phone":"...","site":"...","img":"https://lh3.googleusercontent.com/p/AF1QipPw5-TqG5VqUpowDrvcRtziKntoicnlaAnHOt_6=s1600-w400,https://lh3.googleusercontent.com/p/AF1QipOjZdFJrNQWG2brkxOJZ_w4VqskY6Q3Wvh-vu4Q=s1600-w400,https://lh3.googleusercontent.com/p/AF1QipNR47pIC8yN5FmmozE-X3PkuDa1WRrwAso5-xK_=s1600-w400,"},{"type":"Bác sỹ nha khoa","store":"Phòng Khám Răng Hàm Mặt 56","address":"56 Đường Tân Phú, Khương Đình, Thanh Xuân, Hà Nội, Vietnam","location":"20.99262,105.8262","phone":"+84 96 328 76 27","site":"...","img":""},{"type":"Bác sỹ nha khoa","store":"Phòng Khám Răng Hàm Mặt - Bác Sỹ Nguyễn Đức Xuyên","address":"325, Đường Nguyễn Đức Xuyên, Thanh Xuân, Thượng Đình, Thanh Xuân, Hà Nội, Vietnam","location":"20.9942582,105.8112029","phone":"+84 24 6673 1126","site":"...","img":""},{"type":"Bác sỹ nha khoa","store":"International Dental WE SMILE","address":"124 Lê Trọng Tấn, Khương Mai, Thanh Xuân, Hà Nội, Vietnam","location":"20.9966538,105.8295355","phone":"+84 858 888 386","site":"...","img":"https://lh3.googleusercontent.com/p/AF1QipPzONskAez7RG6Lo67Ia7fDzU6IXFVKKKFsB4m9=s1600-w400,https://lh3.googleusercontent.com/p/AF1QipO_MjiG9ZC-PEhgrtgh21udIRHyBxGt6pPtr7XR=s1600-w400,"},{"type":"Bác sỹ nha khoa","store":"Phòng Khám Răng Hàm Mặt","address":"283A Phố Khương Trung, Khương Trung, Thanh Xuân, Hà Nội 100000, Vietnam","location":"20.994637,105.817116","phone":"+84 98 892 39 98","site":"...","img":""},{"type":"Bác sỹ nha khoa","store":"Smile Dental","address":"01 P. Hạ Đình, Thanh Xuân Trung, Thanh Xuân, Hà Nội, Vietnam","location":"20.9926708,105.8053774","phone":"...","site":"...","img":"https://lh3.googleusercontent.com/p/AF1QipMBe-qMlYxWsz1ekdrB3CIPshXRFAWRXaF8ibZ6=s1600-w400,"},{"type":"Bác sỹ nha khoa","store":"Nha khoa Phương Nam","address":"325 Nguyễn Trãi, Thanh Xuân Nam, Thanh Xuân, Hà Nội, Vietnam","location":"20.992201,105.804693","phone":"+84 94 194 49 77","site":"http://nhakhoaphuongnam.com.vn/","img":"https://lh3.googleusercontent.com/p/AF1QipPG6PFyCQm3fuIX-6QXPV-UZeIqo8i8opymniFn=s1600-w400,"},{"type":"Bác sỹ nha khoa","store":"Nha Khoa Bảo Ngân - Hà Nội","address":"170 Đường Khương Đình, Hạ Đình, Thanh Xuân, Hà Nội, Vietnam","location":"20.9940108,105.8140518","phone":"...","site":"https://timnhakhoa.com/listing/nha-khoa-bao-ngan/","img":"https://lh3.googleusercontent.com/p/AF1QipOfblXQW3u6dwaRoNscG5xNNW6z3je-_N6jUH6b=s1600-w400,"},{"type":"Bác sỹ nha khoa","store":"Trồng Răng Giả Uy Tín","address":"Ngõ 145 Định Công Thượng, Nhân Chính, Thanh Xuân, Hà Nội, Vietnam","location":"21.0040601,105.8123899","phone":"+84 98 730 26 21","site":"https://www.nhakhoaquocteachau.vn/","img":""},{"type":"Bác sỹ nha khoa","store":"Phòng khám răng BS Lâm","address":"252 Nguyễn Trãi, Thượng Đình, Thanh Xuân, Hà Nội 10000, Vietnam","location":"20.997262,105.811796","phone":"+84 91 205 68 08","site":"...","img":""},{"type":"Bác sỹ nha khoa","store":"Nha khoa hà nội","address":"159 Lương Thế Vinh, Mễ Trì, Từ Liêm, Hà Nội, Vietnam","location":"20.9980606,105.7869694","phone":"...","site":"...","img":""},{"type":"Bác sỹ nha khoa","store":"Công ty Luật TNHH Khai Phong và Cộng sự","address":"76/140 Khuất Duy Tiến, Thanh Xuân Bắc, Thanh Xuân, Hà Nội, Vietnam","location":"20.997948,105.797693","phone":"+84 98 262 78 21","site":"http://luatkhaiphong.com/","img":""},{"type":"Bác sỹ nha khoa","store":"Phòng Khám Nha Khoa Huy Chuẩn Số 46 Quan Nhân, Trung Hòa, Cầu Giấy, Hà Nội.","address":"101 Ng. 342 Khương Đình, Hạ Đình, Thanh Xuân, Hà Nội, Vietnam","location":"20.9890254,105.808474","phone":"+84 98 925 53 36","site":"...","img":"https://lh3.googleusercontent.com/p/AF1QipOtrLJ-mWEASmH4SNgY4l-W3mOLitNubiWZ9R1x=s1600-w400,https://lh3.googleusercontent.com/p/AF1QipMK3BYHGWgitciAg9QjraYGGhsw7P1QnZ5F1jj7=s1600-w400,https://lh3.googleusercontent.com/p/AF1QipNr7h_JV6PDEut2gtE2xvOp_0QB9SEUXF5feLMf=s1600-w400,https://lh3.googleusercontent.com/p/AF1QipNswcBozuvBx8SOgKMem_1y09OqfvaTDidkxpLl=s1600-w400,https://lh3.googleusercontent.com/p/AF1QipO2nB3dDSkfCCEjl6qQJF4QgId4bf6pV8Tg16iZ=s1600-w400,https://lh3.googleusercontent.com/p/AF1QipNxIaIdWfFtgSrtDBMGTFrPwBrwKcUciqAgge5R=s1600-w400,https://lh3.googleusercontent.com/p/AF1QipNqP3apUxeaDJxwz0ofHDMUuHQA6iF8ok-B57x0=s1600-w400,https://lh3.googleusercontent.com/p/AF1QipMTUkJA2kHKDSKCWZWbbI31zYx8dRnEHTUltsd2=s1600-w400,https://lh3.googleusercontent.com/p/AF1QipP58_ULVH1_diWbPdrc3RiIq9nCiNUcgUR1lr3I=s1600-w400,https://lh3.googleusercontent.com/p/AF1QipOyMPHVuBTUfV_FwKss-6Wta7Qkq2MFr9RMeOAN=s1600-w400,"},{"type":"Bác sỹ nha khoa","store":"Nha Khoa Thanh Xuân","address":"492 Nguyễn Trãi, Thanh Xuân Trung, Thanh Xuân, Hà Nội, Vietnam","location":"20.9923695,105.8040154","phone":"+84 24 3858 2258","site":"http://www.nhakhoathanhxuan.com/","img":"https://lh3.googleusercontent.com/p/AF1QipOGdokigwdRaulVQOFJgXrndF5vbbYeszi9Fvkm=s1600-w400,"},{"type":"Bác sỹ nha khoa","store":"Nha Khoa Bee Dental","address":"258 Lương Thế Vinh, Trung Văn, Từ Liêm, Hà Nội 10000, Vietnam","location":"20.9925382,105.7940671","phone":"+84 98 985 37 73","site":"https://nha-khoa-bee-dental.business.site/?utm_source=gmb&utm_m","img":""},{"type":"Bác sỹ nha khoa","store":"Nha khoa Hà Nội Family","address":"53 Phố Chính Kinh, Thanh Xuân Trung, Thanh Xuân, Hà Nội, Vietnam","location":"20.9983638,105.8115393","phone":"...","site":"...","img":"https://lh3.googleusercontent.com/p/AF1QipONwY6veoeUIblHDIXpVTyS6cL2RWw8icLhndo=s1600-w400,"},{"type":"Bác sỹ nha khoa","store":"Phòng Khám Răng Hàm Mặt - Bs Đỗ Quang Thanh","address":"203 Khuất Duy Tiến, Thanh Xuân Bắc, Thanh Xuân, Hà Nội, Vietnam","location":"20.9919087,105.8002978","phone":"...","site":"...","img":"https://lh3.googleusercontent.com/p/AF1QipPY8kkJxDA1E3CqAxFomRnVgqVbY02hmorarY8A=s1600-w400,"},{"type":"Bác sỹ nha khoa","store":"Phòng Khám Răng Hàm Mặt Hoàng Gia","address":"234, 234 Quan Nhân, Thanh Xuân Trung, Thanh Xuân, Hà Nội, Vietnam","location":"20.9986718,105.8096976","phone":"+84 24 3558 3077","site":"...","img":""},{"type":"Bác sỹ nha khoa","store":"Nha Khoa VINA","address":"355 Nguyễn Trãi, Thanh Xuân Nam, Thanh Xuân, Hà Nội, Vietnam","location":"20.9916464,105.8042524","phone":"+84 97 778 78 28","site":"https://map.coccoc.com/map/39852116191524073","img":"https://lh3.googleusercontent.com/p/AF1QipNGEDl4xRNYP8LLpZzIMkrhWGi1A38iXj5B3GjC=s1600-w400,"},{"type":"Bác sỹ nha khoa","store":"NHA KHOA PHƯƠNG NAM 325 NGUYỄN TRÃI THANH XUÂN HN","address":"325 Nguyễn Trãi, Thanh Xuân Nam, Thanh Xuân, Hà Nội 100000, Vietnam","location":"20.992201,105.804693","phone":"+84 97 747 44 99","site":"http://nhakhoaphuongnam.com.vn/","img":"https://lh3.googleusercontent.com/p/AF1QipN3zBt_3TQcfuKkK__Qn86Xi7NuFXFfXPSZea8e=s1600-w400,https://lh3.googleusercontent.com/p/AF1QipN1PpeH2UgUlL5VWZAyuwcxkGOUqxsvFPMyOlr2=s1600-w400,https://lh3.googleusercontent.com/p/AF1QipPVdv_Fs_k2zNFKh7GtQotNOONgx5ZwWy5Dp415=s1600-w400,https://lh3.googleusercontent.com/p/AF1QipOMGizF8hijQwtlEDubKv6iO99hunu9zgDAU7it=s1600-w400,https://lh3.googleusercontent.com/p/AF1QipPEvp5_Vf-XpWpWPy0r6nFN_nYvy0WWUXV3R_ai=s1600-w400,https://lh3.googleusercontent.com/p/AF1QipMf9stdbsB2ib6LY9j-7yW1SkPkcgpdF-BCXGS8=s1600-w400,https://lh3.googleusercontent.com/p/AF1QipMTdV03uYVn2-vxJ3zfGgmsNVFl6cfn3uUGJ0HK=s1600-w400,https://lh3.googleusercontent.com/p/AF1QipNjan1k5fDLNcVxcxgxrKxDkTK6ATI7luZbnUrP=s1600-w400,https://lh3.googleusercontent.com/p/AF1QipPBVtMhiyFGwxBE9BVH8y9EPwG5EFE6wQL8JVka=s1600-w400,https://lh3.googleusercontent.com/p/AF1QipOGpNDrXXSbF2K4B88n7OrL8wHaitO6MufDn6D0=s1600-w400,"},{"type":"Bác sỹ nha khoa","store":"Nha Khoa Hà Nội 159","address":"159 Lương Thế Vinh, P. Văn Quán, Thanh Xuân, Hà Nội, Vietnam","location":"20.99072,105.7964","phone":"+84 98 902 67 61","site":"...","img":""},{"type":"Bác sỹ nha khoa","store":"Địa chỉ niềng răng uy tín tại Hà Nội - Nha khoa Phương Nam","address":"325 Nguyễn Trãi, Thanh Xuân Nam, Thanh Xuân, Hà Nội 120036, Vietnam","location":"20.992201,105.804693","phone":"+84 94 194 49 77","site":"https://nhakhoaphuongnam.vn/","img":"https://lh3.googleusercontent.com/p/AF1QipNPePfFZe2yND5Uewok6Ddn_INJ_cS8s1zk1_6x=s1600-w400,https://lh3.googleusercontent.com/p/AF1QipPS1nAqXxAyZcE20nkLtzfokDOiUYIvQOD1lfsn=s1600-w400,https://lh3.googleusercontent.com/p/AF1QipPQtJS1HNdCBWYYYNHc0F00jK68ZTFQkZ1OmPKK=s1600-w400,https://lh3.googleusercontent.com/p/AF1QipOqJPH1Bsbn_Zj-Qrzl0XTh7El-1xSjidz2wKr2=s1600-w400,https://lh3.googleusercontent.com/p/AF1QipMjeVkAoa4w2ODopuTyTsb8gM94hsLUAX3qrHQj=s1600-w400,https://lh3.googleusercontent.com/p/AF1QipNZNfvupPTUUF_EGf9bpxUGKEuxE8QF6m_kup2N=s1600-w400,https://lh3.googleusercontent.com/p/AF1QipOXzq53bCd1en5fLVRnwSnRESJ7BchxkNEE2yw4=s1600-w400,https://lh3.googleusercontent.com/p/AF1QipP3FUjsLtx9UlNLAZqdO2KlCIoklsyABLmLdrqC=s1600-w400,https://lh3.googleusercontent.com/p/AF1QipOOyAfEucwoU5qG52ZjqPb6KqDBaC9iguHcd4hY=s1600-w400,https://lh3.googleusercontent.com/p/AF1QipNtnwlDqqZNjf4k-Kl1ClVV4XcZ3mqzgIWe7TvJ=s1600-w400,"},{"type":"Bác sỹ nha khoa","store":"Minh Thu Dental","address":"92 Phố Hoàng Ngân, Trung Hoà, Cầu Giấy, Hà Nội, Vietnam","location":"21.0088442,105.8077008","phone":"...","site":"...","img":""},{"type":"Bác sỹ nha khoa","store":"NHA KHOA PHƯƠNG ANH","address":"520 Nguyễn Trãi, Thanh Xuân Trung, Thanh Xuân, Hà Nội, Vietnam","location":"20.9923426,105.8035818","phone":"+84 24 6268 7687","site":"http://nhakhoaphuonganh.com/","img":"https://lh3.googleusercontent.com/p/AF1QipPTn96o_GVxT530YhG-96JA3ZyZZez7oMxcLjDq=s1600-w400,https://lh3.googleusercontent.com/p/AF1QipMwk3CidASeFhRa9m60nouIYSkPTyAC3cjHVbep=s1600-w400,https://lh3.googleusercontent.com/p/AF1QipPDQndqelizHzS378ADp1fIEQD99YGAJ2vhp6IR=s1600-w400,https://lh3.googleusercontent.com/p/AF1QipMzaeRPFvJRSXii-G5Zmt2vFEKNSeqYzUHDcejD=s1600-w400,https://lh3.googleusercontent.com/p/AF1QipMzWQIVXWT87_JHEkXYn6ZEHQ_b94bhSoOLq_EA=s1600-w400,https://lh3.googleusercontent.com/p/AF1QipPOBQch4bQdj1edEDJvrv8DShdktaysbjzB98ab=s1600-w400,https://lh3.googleusercontent.com/p/AF1QipM_zkpKaGjsf2ZnbjkyAmxG6EBBokWcYPBETHnF=s1600-w400,https://lh3.googleusercontent.com/p/AF1QipMtuz4R9bck5hYocdWVGR9xlV6WWZ82YvtwBmQt=s1600-w400,https://lh3.googleusercontent.com/p/AF1QipP44qyR37aA07K387zB8m0fnV2FGy6zT6CAt4pt=s1600-w400,https://lh3.googleusercontent.com/p/AF1QipM_DqLsdyhTSiNbWM92FSGSC6CijA6LtuHMO6N9=s1600-w400,"},{"type":"Bác sỹ nha khoa","store":"Nha khoa Minh Thu - nắn chỉnh răng và cấy ghép implant","address":"92 Phố Hoàng Ngân, Trung Hoà, Cầu Giấy, Hà Nội, Vietnam","location":"21.0088442,105.8077008","phone":"+84 24 3556 8837","site":"http://www.nhakhoaminhthu.com/","img":""},{"type":"Bác sỹ nha khoa","store":"Tran Quoc Toan Dental Clinic","address":"193 Vũ Hữu, Street, Thanh Xuân, Hà Nội, Vietnam","location":"20.99553,105.7959662","phone":"...","site":"...","img":""},{"type":"Bác sỹ nha khoa","store":"TRỒNG RĂNG SỨ UY TÍN","address":"171 Khuất Duy Tiến, Nhân Chính, Thanh Xuân, Hà Nội, Vietnam","location":"21.0000259,105.796065","phone":"+84 98 730 26 21","site":"...","img":""},{"type":"Bác sỹ nha khoa","store":"Nha Khoa Trung Hiếu","address":"102 E7, Khu tập thể Thanh Xuân Bắc, Thanh Xuân, Hà Nội, Vietnam","location":"20.99106,105.7988","phone":"+84 98 656 90 69","site":"...","img":""},{"type":"Bác sỹ nha khoa","store":"Nha Khoa Toàn Tâm","address":"193, Vũ Hữu, Quận Thanh Xuân, Thành Phố Hà Nội, Trung Văn, Nam Từ Liêm, Hà Nội, Vietnam","location":"20.995466,105.795959","phone":"+84 98 375 15 19","site":"...","img":"https://lh3.googleusercontent.com/p/AF1QipNGJY1ZmFf1FqRXJy5l5HHdTjsEENd9Ujv2ZW-n=s1600-w400,https://lh3.googleusercontent.com/p/AF1QipPANxfDKFF4ltYxm--RfRo7P1_Kyz2548Cb_ySz=s1600-w400,https://lh3.googleusercontent.com/p/AF1QipNf8tBbq_zFjsVFxV7BIUJUX0OvteeTCmjF6MPx=s1600-w400,https://lh3.googleusercontent.com/p/AF1QipNUNeEPgHF7uG_AxvgnPnB1IuPAw4MxSj7J_JdR=s1600-w400,https://lh3.googleusercontent.com/p/AF1QipPHrPypdJpiqWfOG3uSZO38inRnO9YgU8J8Osaj=s1600-w400,https://lh3.googleusercontent.com/p/AF1QipMkxOc8C_UlcjBL2ARUT0sW2POs1EiooMzwHyGu=s1600-w400,https://lh3.googleusercontent.com/p/AF1QipOE-KomP1sQPStnesvyzuSIihfJV1mU-7EgxkIR=s1600-w400,"},{"type":"Bác sỹ nha khoa","store":"Nha Khoa Linh Anh","address":"117D1 Khu Tập Thể, Thanh Xuân Bắc, Thanh Xuân, Hà Nội, Vietnam","location":"20.9938389,105.800156","phone":"+84 98 257 32 41","site":"...","img":"https://lh3.googleusercontent.com/p/AF1QipPn958vLv7O_Syou9YK4heJBI2LwKxPp9Prt2Zn=s1600-w400,"},{"type":"Bác sỹ nha khoa","store":"NHA KHOA MINH THU","address":"92 Phố Hoàng Ngân, Trung Hoà, Cầu Giấy, Hà Nội, Vietnam","location":"21.0088442,105.8077008","phone":"...","site":"...","img":""},{"type":"Bác sỹ nha khoa","store":"Nha Khoa Tùng Ngọc","address":"175 Quan Nhân, Nhân Chính, Thanh Xuân, Hà Nội, Vietnam","location":"21.0034389,105.811084","phone":"+84 98 113 61 61","site":"...","img":""},{"type":"Bác sỹ nha khoa","store":"Nha Khoa 68 Nguyễn Huy Tưởng","address":"294 Nguyễn Huy Tưởng, Thanh Xuân Trung, Thanh Xuân, Hà Nội, Vietnam","location":"20.99701,105.8034","phone":"+84 888 631 333","site":"...","img":""},{"type":"Bác sỹ nha khoa","store":"Nha Khoa Minh Thu","address":"92 Phố Hoàng Ngân, Trung Hoà, Cầu Giấy, Hà Nội, Vietnam","location":"21.0088442,105.8077008","phone":"+84 24 3556 8837","site":"http://www.nhakhoaminhthu.com/index.php?option=com_content&view","img":""},{"type":"Bác sỹ nha khoa","store":"Nha Khoa ĐÔNG NAM Á","address":"166 Đ. Nguyễn Tuân, Thanh Xuân Trung, Thanh Xuân, Hà Nội 100000, Vietnam","location":"20.9992143,105.8028375","phone":"+84 768 234 999","site":"http://nhakhoadongnama.vn/","img":"https://lh3.googleusercontent.com/p/AF1QipODADjHaITtIE1UQzoIfdWVWIcPElUBF7N2cAg-=s1600-w400,https://lh3.googleusercontent.com/p/AF1QipNVD1JgP8FXbK4pDW3wV3LRe2KoKo0pbJSeMPnk=s1600-w400,https://lh3.googleusercontent.com/p/AF1QipOagJMd-27DiFRym0l0FulX79_SkjgwAaPtWduK=s1600-w400,https://lh3.googleusercontent.com/p/AF1QipPngzMJx20jZniaU80sH9gmfXXbFKLmsuaP7MIc=s1600-w400,https://lh3.googleusercontent.com/p/AF1QipN5RjH0M_vK7ktHjRwdSgGsalxsxh2TEd9IMQjG=s1600-w400,https://lh3.googleusercontent.com/p/AF1QipPinDoXFhHx7vVin8dl3xOXn4v8LrB2Yq3xfYdG=s1600-w400,https://lh3.googleusercontent.com/p/AF1QipNRCSQdCrMgq07hgRq5KOzqOoAHBnSFczo7X_Nm=s1600-w400,https://lh3.googleusercontent.com/p/AF1QipOg74uCFbreNJ26ccUlTtRXxUef6l_POVULdJkw=s1600-w400,https://lh3.googleusercontent.com/p/AF1QipPBUR2oifA8lKcxdpy9-MgMy6lPGyOQZ3Wt2pp-=s1600-w400,https://lh3.googleusercontent.com/p/AF1QipP6lJ3Z_ofdHCd85Kow2zevOqZ8gX96OJn3rsNN=s1600-w400,"},{"type":"Bác sỹ nha khoa","store":"Nha khoa thẩm mỹ Seoul","address":"237 Khuất Duy Tiến, Nhân Chính, Thanh Xuân, Hà Nội 100000, Vietnam","location":"21.000442,105.79573","phone":"+84 853 128 222","site":"http://nhakhoaseoul.vn/","img":"https://lh3.googleusercontent.com/p/AF1QipOZfDl30g5GAXODxhE8zkzaVFO9VOgUpi_J7zCD=s1600-w400,https://lh3.googleusercontent.com/p/AF1QipMcqI9Eb4cG8A2X_qs9cNnHbAEC4JElq8m8lyF3=s1600-w400,https://lh3.googleusercontent.com/p/AF1QipNwMtuD2cikFHdqgRJ0SOtWqOfpD_25ha3x3DK9=s1600-w400,https://lh3.googleusercontent.com/p/AF1QipNYEB4ryhghFQiyze5UjGi13fYx-VNoCYsY21Hr=s1600-w400,https://lh3.googleusercontent.com/p/AF1QipPjO8-4_N3RANLAhxm2YCcrlFliYv8KOHSxXbyj=s1600-w400,https://lh3.googleusercontent.com/p/AF1QipOubVLpsM0IHW9hAWQrN6EYqD7FZ4Rh9nVIhpKR=s1600-w400,https://lh3.googleusercontent.com/p/AF1QipM7u-2y_9GEJt2vTecoBLVts5Zdgen6bz7GRDrZ=s1600-w400,https://lh3.googleusercontent.com/p/AF1QipNKUnCEcdCu_cSM2F_-vc5sXmMNznTSSMRE4THP=s1600-w400,https://lh3.googleusercontent.com/p/AF1QipNUNcXHgrjFqgx6pfY_tQEE4e1dOiSTKr-c1Dre=s1600-w400,https://lh3.googleusercontent.com/p/AF1QipN4Wnh8dGgdPw05NyujUyfUflRQ4Xix8J3zDNG8=s1600-w400,"},{"type":"Bác sỹ nha khoa","store":"nha khoa Minh Thu, Hoàng Ngân, Trung Hoà, Cầu Giấy, Hanoi","address":"92 Phố Hoàng Ngân, Trung Hoà, Cầu Giấy, Hà Nội, Vietnam","location":"21.0088442,105.8077008","phone":"...","site":"http://www.nhakhoaminhthu.com/","img":""},{"type":"Bác sỹ nha khoa","store":"Nha khoa. Dr Lieu","address":"81 Vũ Trọng Phụng, Thanh Xuân Trung, Thanh Xuân, Hà Nội, Vietnam","location":"21.0007376,105.8066255","phone":"+84 24 6687 0204","site":"http://nhakhoadrlieu.vn/","img":"https://lh3.googleusercontent.com/p/AF1QipOJ9sAVtxu-lCAuik8R6WjNunPntSgtkKqmijG1=s1600-w400,"},{"type":"Bác sỹ nha khoa","store":"Nha khoa 119 Hoàng Ngân","address":"119 Phố Hoàng Ngân, Nhân Chính, Thanh Xuân, Hà Nội 100000, Vietnam","location":"21.007781,105.8090399","phone":"+84 91 201 25 16","site":"https://nha-khoa-119-hoang-ngan.business.site/?utm_source=gmb&u","img":"https://lh3.googleusercontent.com/p/AF1QipP8VVwNIfEpDxviM4y6xKpmA02o7TN9_PqE7DIC=s1600-w400,https://lh3.googleusercontent.com/p/AF1QipM17pkt2AFpNsEaU9gdJPfXVCyBNazKkeJC7PbM=s1600-w400,https://lh3.googleusercontent.com/p/AF1QipOiZnBSRBENM3KRsCdWL-2wPAkHf9VRJhzFXZU7=s1600-w400,https://lh3.googleusercontent.com/p/AF1QipMywhiC1DHrT298-kc0HynMMIK7-QCITwAHfrS4=s1600-w400,https://lh3.googleusercontent.com/p/AF1QipPFDULOg-cn6E6v6FbRGFvcsrt7cRFGMZiBYoE4=s1600-w270,"},{"type":"Bác sỹ nha khoa","store":"thuộc vềnha Khoa Minh Thu, Hoàng Ngân, Trung Hoà, Cầu Giấy, Hanoi","address":"92 Phố Hoàng Ngân, Trung Hoà, Cầu Giấy, Hà Nội, Vietnam","location":"21.0088442,105.8077008","phone":"...","site":"...","img":""},{"type":"Bác sỹ nha khoa","store":"Phòng Khám Răng Hàm Mặt Bác Sĩ Nguyễn Đăng Dự","address":"78, Đường Võ Trọng Phụng, Thanh Xuân Trung, Thanh Xuân, Hà Nội, Vietnam","location":"21.0001457,105.8065968","phone":"+84 91 265 51 80","site":"...","img":""},{"type":"Bác sỹ nha khoa","store":"Nha Khoa Minh Thu, Hoàng Ngân, Trung Hoà, Cầu Giấy, Hanoi","address":"92 Phố Hoàng Ngân, Trung Hoà, Cầu Giấy, Hà Nội, Vietnam","location":"21.0088442,105.8077008","phone":"+84 24 3556 8837","site":"http://www.nhakhoaminhthu.com/","img":""},{"type":"Bác sỹ nha khoa","store":"nha khoa Minh Thu","address":"92 Phố Hoàng Ngân, Trung Hoà, Cầu Giấy, Hà Nội, Vietnam","location":"21.0088442,105.8077008","phone":"+84 24 3556 8837","site":"http://www.nhakhoaminhthu.com/","img":""},{"type":"Bác sỹ nha khoa","store":"Trung Tâm implant -nha khoa Minh Thu","address":"92 Phố Hoàng Ngân, Trung Hoà, Cầu Giấy, Hà Nội, Vietnam","location":"21.0088442,105.8077008","phone":"+84 24 3556 8837","site":"http://www.nhakhoaminhthu.com/","img":""},{"type":"Bác sỹ nha khoa","store":"Nha khoa Han Dental","address":"Số 2, Ngõ 21 Lê Văn Lương, Nhân Chính, Thanh Xuân, Hà Nội, Vietnam","location":"21.0059344,105.8069853","phone":"+84 899 612 468","site":"https://nhakhoahan.business.site/?utm_source=gmb&utm_medium=ref","img":"https://lh3.googleusercontent.com/p/AF1QipOa7sPFXZ3H8F_lxwepOVEdzZyq357XyOv2pPkh=s1600-w400,https://lh3.googleusercontent.com/p/AF1QipOABakJ9hmYnwIz8arvEjzFKNxurgQ9RAbuAu08=s1600-w400,https://lh3.googleusercontent.com/p/AF1QipNQysRWAgYEzpYyQikz5B9btFF4e_gNlM22qE3c=s1600-w400,https://lh3.googleusercontent.com/p/AF1QipMoiued_IIDyoIk9X__CqK-1ZLZhYctec5NIOtl=s1600-w400,https://lh3.googleusercontent.com/p/AF1QipOUf5rWyzNc3a_HA0EbFLeguXpspjLvQD2LyKVd=s1600-w400,https://lh3.googleusercontent.com/p/AF1QipORV8x1_A81IHsJ0UFhXfttSwK9gIWt1PpTTs8y=s1600-w400,https://lh3.googleusercontent.com/p/AF1QipMEqbgsHzUNF3iIA6nov_aSIdYubtiFWojhc4XQ=s1600-w400,https://lh3.googleusercontent.com/p/AF1QipPuKSv6lRkTibNOCWUL-hOwoc1EOyBeCxC4SNWu=s1600-w400,https://lh3.googleusercontent.com/p/AF1QipNJBjbqWDPEJPfv7PkL5Yde3WVjufDQWk9avy2A=s1600-w400,https://lh3.googleusercontent.com/p/AF1QipOzSomBPwzoxjMLH3Tmd5Mfg3MyWY2UbWZt3tu1=s1600-w400,"},{"type":"Bác sỹ nha khoa","store":"Dental Clinic","address":"176, Bo De Street, Long Bien District, Bồ Đề, Long Biên, Hà Nội, Vietnam","location":"21.0362533,105.8744679","phone":"+84 98 696 91 25","site":"...","img":""},{"type":"Bác sỹ nha khoa","store":"Trung tâm implant nha khoa Minh Thu","address":"92 Phố Hoàng Ngân, Trung Hoà, Cầu Giấy, Hà Nội, Vietnam","location":"21.0088442,105.8077008","phone":"+84 24 3556 8837","site":"http://www.nhakhoaminhthu.com/","img":""},{"type":"Bác sỹ nha khoa","store":"Nha Khoa Minh Thu","address":"92 Phố Hoàng Ngân, Trung Hoà, Cầu Giấy, Hà Nội, Vietnam","location":"21.0088442,105.8077008","phone":"+84 24 3556 8837","site":"http://www.nhakhoaminhthu.com/","img":""},{"type":"Bác sỹ nha khoa","store":"Minh Thu Dental","address":"92 Phố Hoàng Ngân, Trung Hoà, Cầu Giấy, Hà Nội, Vietnam","location":"21.0088442,105.8077008","phone":"...","site":"...","img":""},{"type":"Bác sỹ nha khoa","store":"minh thu dental","address":"92 Phố Hoàng Ngân, Trung Hoà, Cầu Giấy, Hà Nội, Vietnam","location":"21.0088442,105.8077008","phone":"+84 24 3556 8837","site":"http://www.nhakhoaminhthu.com/","img":"https://lh3.googleusercontent.com/p/AF1QipP_DH4OCp1lWzrdXeJBSy-e5CVKlzM1y-YrRm4h=s1600-w400,"},{"type":"Bác sỹ nha khoa","store":"Dental Minh Thu","address":"92 Phố Hoàng Ngân, Trung Hoà, Cầu Giấy, Hà Nội, Vietnam","location":"21.0088442,105.8077008","phone":"...","site":"...","img":""},{"type":"Bác sỹ nha khoa","store":"Công Ty Cp Nha Khoa Thẩm Mỹ Quốc Tế Paris","address":"720, 8 Nguyễn Văn Cừ, Bồ Đề, Long Biên, Hà Nội, Vietnam","location":"21.0399671,105.8670015","phone":"...","site":"...","img":""},{"type":"Bác sỹ nha khoa","store":"nha khoa Minh Thu, Hoàng Ngân, Trung Hoà, Cầu Giấy","address":"92 Phố Hoàng Ngân, Trung Hoà, Cầu Giấy, Hà Nội, Vietnam","location":"21.0088442,105.8077008","phone":"+84 24 3556 8837","site":"http://www.nhakhoaminhthu.com/","img":""},{"type":"Bác sỹ nha khoa","store":"Dịch Vụ Trồng Răng Tiền Phong","address":"138 Ngọc Lâm, Long Biên, Hà Nội 100000, Vietnam","location":"21.045325,105.8698361","phone":"+84 90 414 77 04","site":"...","img":""},{"type":"Bác sỹ nha khoa","store":"Nha Khoa Thẩm Mỹ Răng Hàm Mặt","address":"35 Nhân Hòa, Thanh Xuân Trung, Thanh Xuân, Hà Nội, Vietnam","location":"21.0019926,105.8079145","phone":"+84 91 416 02 75","site":"...","img":""},{"type":"Bác sỹ nha khoa","store":"Minh Thu Dental","address":"92 Phố Hoàng Ngân, Trung Hoà, Cầu Giấy, Hà Nội, Vietnam","location":"21.0088442,105.8077008","phone":"...","site":"...","img":""},{"type":"Bác sỹ nha khoa","store":"Nha Khoa Minh Thu","address":"92 Phố Hoàng Ngân, Trung Hoà, Cầu Giấy, Hà Nội, Vietnam","location":"21.0088442,105.8077008","phone":"...","site":"...","img":""},{"type":"Bác sỹ nha khoa","store":"Phòng Khám Răng Hàm Mặt 35","address":"35 Phố Tư Đình, Long Biên, Hà Nội, Vietnam","location":"21.02902,105.8846","phone":"+84 97 550 22 92","site":"...","img":""},{"type":"Bác sỹ nha khoa","store":"Trung Tâm Thẩm Mỹ Răng Hà Nội","address":"285, Tổ 17, Đường Lâm Du, Phường Bồ Đề, Quận Long Biên, Bồ Đề, Long Biên, Hà Nội, Vietnam","location":"21.0339943,105.8756847","phone":"+84 91 233 12 93","site":"...","img":""},{"type":"Bác sỹ nha khoa","store":"nha khoa MInh Thu","address":"92 Phố Hoàng Ngân, Trung Hoà, Cầu Giấy, Hà Nội, Vietnam","location":"21.0088442,105.8077008","phone":"...","site":"...","img":""},{"type":"Bác sỹ nha khoa","store":"Nha Khoa Định Công","address":"246 Định Công, Hoàng Mai, Hà Nội, Vietnam","location":"20.9825999,105.8338387","phone":"+84 98 340 67 72","site":"...","img":"https://lh3.googleusercontent.com/p/AF1QipP12rMlx3HEoqIn5wq4h_8Nhhx10uSSJ8r4TkwT=s1600-w400,https://lh3.googleusercontent.com/p/AF1QipOTh_78GWiW7iXNilvPg4HYA6u27EAGw6N628Pc=s1600-w400,https://lh3.googleusercontent.com/p/AF1QipP-eW7eAjzIpw-L23gTs-UuYQrQChFomqLyf65c=s1600-w400,https://lh3.googleusercontent.com/p/AF1QipOKUJ8MKl-CNxIB6DoWSHXmMKTuc6o0jrfO5iv7=s1600-w400,https://lh3.googleusercontent.com/p/AF1QipNI6eTi_fPlFppcaaoFms1Rx06K00X5vX_J2343=s1600-w400,"},{"type":"Bác sỹ nha khoa","store":"Bàn thí nghiệm","address":"Số 100A3 Đại Kim 黄梅, Đại Kim, Hoàng Mai, Hà Nội, Vietnam","location":"20.9765522,105.8347919","phone":"+84 98 728 10 07","site":"http://bànthínghi?m.vn/","img":"https://lh3.googleusercontent.com/p/AF1QipONk4FREyIEqHF-IzfHFLnRQOefnZ3r62trSko=s1600-w400,https://lh3.googleusercontent.com/p/AF1QipPBrXPJnTxKrPJGgA4tcEyBiyQ_KvM_T-yXFj8=s1600-w400,https://lh3.googleusercontent.com/p/AF1QipN6z0SMOmPzQgHR_4RUI590cuLTlJy0X7VmJ1Q=s1600-w400,https://lh3.googleusercontent.com/p/AF1QipNZ2lPMy01Fa-fSIULDDkiPmNG593MxrTu6rAQ=s1600-w300,https://lh3.googleusercontent.com/p/AF1QipPGxHqRfNrXKmhjFZklEheOFGfGn_sFlWpLGEI=s1600-w400,https://lh3.googleusercontent.com/p/AF1QipN0EF6DDRydK6BjwRmFXRvLaYlVpZ-YwRgMuC4=s1600-w400,https://lh3.googleusercontent.com/p/AF1QipMiPf5R26UXEi3tb_-RfHvQ1ZSpnq9ZNrErB3I=s1600-w400,https://lh3.googleusercontent.com/p/AF1QipOFyLF3GQrwLtvMm2O-G_8RRmAK1-5VIYzSWBc=s1600-w400,https://lh3.googleusercontent.com/p/AF1QipPDQ5oiYWV0KtR7Q3UVweU-upRXd99Ast3w8E0=s1600-w400,https://lh3.googleusercontent.com/p/AF1QipOVDi7IjbnJVW574BzyHRRF8acrNRZ8mZoxOXk=s1600-w300,"},{"type":"Bác sỹ nha khoa","store":"Dr. Tran Chung Anh Dental Clinic","address":"108 Ngọc Lâm, Long Biên, Hà Nội, Vietnam","location":"21.045549,105.8695892","phone":"+84 91 352 45 90","site":"...","img":""},{"type":"Bác sỹ nha khoa","store":"Dental Minh Thu","address":"92 Hoàng Ngân, 193 C3 Bà Triệu, Trung Hoà, Cầu Giấy, Hà Nội, Vietnam","location":"21.008689,105.807761","phone":"+84 24 3556 8837","site":"http://www.nhakhoaminhthu.com/","img":"https://lh3.googleusercontent.com/p/AF1QipOYgc4IShinTf2881oSLwxJuFRzgce3BgFwaGrI=s1600-w400,https://lh3.googleusercontent.com/p/AF1QipPZC1oUC9A2Q4A0DGrasyiyRTFhDnObrN6yp6v5=s1600-w400,https://lh3.googleusercontent.com/p/AF1QipNEjEP7lqWljmxY_izraETjMje7sZsnbkQQKf76=s1600-w400,https://lh3.googleusercontent.com/p/AF1QipMPVtZM2jnRx1IVxeMAsh3eJrGa3fN_ubZO0lKH=s1600-w400,https://lh3.googleusercontent.com/p/AF1QipPfSaDbn-yps4sxBP0PXF0VqNP5kI9nd1eRFNuy=s1600-w400,https://lh3.googleusercontent.com/p/AF1QipOAa_iEwgVBWupI1eLYmAT0JOISVvn7goA0Qu_w=s1600-w400,https://lh3.googleusercontent.com/p/AF1QipPlzsO9zfzf31pNDe6vz7pGxQlYqUXYAYqYADib=s1600-w400,https://lh3.googleusercontent.com/p/AF1QipMArbMmD4niVQ9m9gd3dgWFSl6v3cx9Q5Q8xJhl=s1600-w400,https://lh3.googleusercontent.com/p/AF1QipPSVCqmpN_DkXCfhoEPP-wdGEy8ig3IVW1yvOpV=s1600-w400,https://lh3.googleusercontent.com/p/AF1QipMFIHaUFxixZN0SHN7q7HE7fIok2Q4D-jstY2YN=s1600-w400,"},{"type":"Bác sỹ nha khoa","store":"PHÒNG KHÁM RĂNG UY TÍN","address":"3 Đ. Lâm Du, Bồ Đề, Long Biên, Hà Nội, Vietnam","location":"21.0392376,105.8670694","phone":"+84 98 730 26 21","site":"...","img":""},{"type":"Bác sỹ nha khoa","store":"Nha khoa Đính đá vào răng E.Las Paris Hà Nội","address":"39 Quang Trung, Trần Hưng Đạo, Hoàn Kiếm, Hà Nội, Vietnam","location":"21.0199889,105.8481044","phone":"+84 24 7302 2226","site":"http://dinhdavaorang.com/","img":""},{"type":"Bác sỹ nha khoa","store":"Biển Quảng cáo – Công ty Quảng cáo Applus","address":"242 Đường Giáp Bát, Giáp Bát, Hoàng Mai, Hà Nội 100000, Vietnam","location":"20.9829509,105.8442536","phone":"+84 815 838 383","site":"http://applus.vn/","img":""},{"type":"Bác sỹ nha khoa","store":"Phòng Khám Nha Khoa Phú Mỹ Hưng","address":"64 Long Biên 1, Ngọc Lâm, Long Biên, Hà Nội, Vietnam","location":"21.0456115,105.8684654","phone":"+84 24 6672 8906","site":"...","img":"https://lh3.googleusercontent.com/p/AF1QipN_GqmJKycOir2vCNukuwqkOF9rTpGv0TSA5PS4=s1600-w400,"},{"type":"Bác sỹ nha khoa","store":"Nha Khoa 123 Ngọc Lâm","address":"123 Ngọc Lâm, Long Biên, Hà Nội, Vietnam","location":"21.0452495,105.8686648","phone":"+84 24 3873 3910","site":"...","img":"https://lh3.googleusercontent.com/p/AF1QipPsP6sbXOkeZRV3Y7gQ8wNpbwNg-ab8eE53Hyge=s1600-w400,https://lh3.googleusercontent.com/p/AF1QipPRsiNHl8fdfr9MGxv_Ar4kgSXzHUe_79RASqLM=s1600-w400,"},{"type":"Bác sỹ nha khoa","store":"Nha Khoa Diamond Nacera","address":"403 Đ. Bạch Đằng, Chương Dương Độ, Hoàn Kiếm, Hà Nội 100000, Vietnam","location":"21.0257829,105.86181","phone":"+84 96 567 33 33","site":"...","img":"https://lh3.googleusercontent.com/p/AF1QipOCDVFq-JpLnMyDndJ2ZiyM2wOHLexAPPwLituh=s1600-w400,https://lh3.googleusercontent.com/p/AF1QipN6xSnwPwdYEp4ccoAbbzjetFmSnPfAJubGSqgi=s1600-w400,https://lh3.googleusercontent.com/p/AF1QipMd4fC8ORhPrUws-Yd5e-JTP4JVfULyS5gWrgO1=s1600-w400,"},{"type":"Bác sỹ nha khoa","store":"Nha Khoa Thái Bình","address":"2 Ngách 245/138, Định Công, Hoàng Mai, Hà Nội, Vietnam","location":"20.97765,105.8346","phone":"+84 24 6686 2962","site":"...","img":""},{"type":"Bác sỹ nha khoa","store":"Artist Dental - Viện Nghệ Thuật Nha Khoa","address":"15 Lê Văn Thiêm, Nhân Chính, Thanh Xuân, Hà Nội 100000, Vietnam","location":"21.001377,105.8028872","phone":"+84 866 610 386","site":"...","img":"https://lh3.googleusercontent.com/p/AF1QipNzP8NlbFPUuI9M_kYWIkETwE8KmYBcHlVPxHqN=s1600-w400,https://lh3.googleusercontent.com/p/AF1QipOLpIa1Wq3qOPsRcaONm5XuOY5w_pWN5z__P6Hw=s1600-w400,https://lh3.googleusercontent.com/p/AF1QipO-W1fGgEPt4EJSL7BSzkMpbicxLDCK2X7RHjcK=s1600-w400,https://lh3.googleusercontent.com/p/AF1QipO5BS0H41OS579TnjA3dSDzI2bC6GMAwkUvf9Mn=s1600-w400,https://lh3.googleusercontent.com/p/AF1QipPpbYwL6xuPzYEaepZ9NJwnVGYzs2qVCsKMjaRP=s1600-w400,https://lh3.googleusercontent.com/p/AF1QipPwE9qWRr2PsPKgyS89zAsrWxNX7mULGYGpx_IP=s1600-w400,https://lh3.googleusercontent.com/p/AF1QipOSRZFxMFFZ1vI8kg_tXdnhiQWkt5D3gNPwwUf7=s1600-w400,https://lh3.googleusercontent.com/p/AF1QipOlNZaSnGNIgN-uA0egTIBmnWpmPGt_xN8e1jh9=s1600-w400,https://lh3.googleusercontent.com/p/AF1QipN_4VC58IJncWi_98VDVjptof-khfVSdgvhBfKk=s1600-w400,https://lh3.googleusercontent.com/p/AF1QipNyhdt739zv1VP3Atluf8iau17OamCpfdaEgUMV=s1600-w400,"},{"type":"Bác sỹ nha khoa","store":"Le Nguyen Dentistry","address":"58 Hoàng Như Tiếp, Bồ Đề, Long Biên, Hà Nội, Vietnam","location":"21.0437521,105.875625","phone":"+84 24 6673 4834","site":"...","img":""},{"type":"Bác sỹ nha khoa","store":"NHA KHOA","address":"30 Nguyễn Như Đổ, Văn Miếu, Đống Đa, Hà Nội, Vietnam","location":"21.026626,105.8391407","phone":"+84 98 730 26 21","site":"https://www.nhakhoaquocteachau.vn/","img":"https://lh3.googleusercontent.com/p/AF1QipNj8u5SmSDmFYeYcxyoppP9Eh3KczR7s94yeTtu=s1600-w400,"},{"type":"Bác sỹ nha khoa","store":"Phòng Khám Bệnh Tư Nhân Răng - Hàm - Mặt","address":"79/24, Đường Kim Đồng, Phường Giáp Bát, Quận Hoàng Mai, Giáp Bát, Hoàng Mai, Hà Nội, Vietnam","location":"20.9804727,105.8436366","phone":"+84 98 865 49 99","site":"...","img":"https://lh3.googleusercontent.com/p/AF1QipO_qQoCa3OkOOizQUuk92WRlAC4InIMf4IrxZNI=s1600-w400,"},{"type":"Bác sỹ nha khoa","store":"PHÒNG KHÁM NHA KHOA HÀ NỘI","address":"3 Đ. Lâm Du, Bồ Đề, Long Biên, Hà Nội, Vietnam","location":"21.0392376,105.8670694","phone":"+84 98 730 26 21","site":"...","img":""},{"type":"Bác sỹ nha khoa","store":"Công ty cổ phần thương mại Thanh Nam","address":"176 Đ. Nguyễn Tuân, Nhân Chính, Thanh Xuân, Hà Nội, Vietnam","location":"21.0005542,105.8019736","phone":"+84 24 3514 4416","site":"http://www.thanhnam.com.vn/","img":""},{"type":"Bác sỹ nha khoa","store":"Phòng Khám Nha Khoa Tiền Phong","address":"138, Đường Ngọc Lâm, Long Biên, Hà Nội, Vietnam","location":"21.0458744,105.869383","phone":"+84 24 3873 2516","site":"...","img":""},{"type":"Bác sỹ nha khoa","store":"Nha Khoa Mai Anh","address":"688 Trương Định, Thịnh Liệt, Hoàng Mai, Hà Nội, Vietnam","location":"20.9807134,105.8449352","phone":"+84 24 6294 4368","site":"...","img":"https://lh3.googleusercontent.com/p/AF1QipNU3kLxXW5qjCMi9WQfQO7gDQGvKXkQuArKFuGp=s1600-w400,https://lh3.googleusercontent.com/p/AF1QipOGJOusTSFplZr2PNPfw1xWJ_LA-ZFQqQ1dt6DH=s1600-w400,"},{"type":"Bác sỹ nha khoa","store":"Nha Khoa Win Smile","address":"51B Đường Lê Duẩn, Khâm Thiên, Hoàn Kiếm, Hà Nội 10000, Vietnam","location":"21.0266386,105.8415964","phone":"+84 96 668 82 34","site":"http://winsmile.vn/","img":"https://lh3.googleusercontent.com/p/AF1QipM8bdwgZ1GcAm8YPwxT5c7JZI6qDkW5qfJXiRKI=s1600-w400,https://lh3.googleusercontent.com/p/AF1QipMUShzbfcgHJ8lCEWBVS9MJ4cx9EhgoqqUotRb6=s1600-w400,https://lh3.googleusercontent.com/p/AF1QipPmwyjuKDWX3C7AnwjW6ek512ftRCcwOhnwZEXG=s1600-w400,https://lh3.googleusercontent.com/p/AF1QipOBDbZoaCeByPvLCHTCnspM8403ZtWvxluCRXO4=s1600-w400,https://lh3.googleusercontent.com/p/AF1QipMGWSL6tphRnOeolQ3SFxn19UiLfM-e4DdWnD6F=s1600-w400,https://lh3.googleusercontent.com/p/AF1QipMoz13Lo_xr8uSdMld3JP3E4LkWQ8M0E1uK4stn=s1600-w400,https://lh3.googleusercontent.com/p/AF1QipP3E04WbwyOIwMUqkEGCAAZ0z3Dm_kfRfNtO6ZB=s1600-w400,https://lh3.googleusercontent.com/p/AF1QipO30ZWFUjs6HYL5W2r5yiYrb3OBcF9ts3DMo_KD=s1600-w400,https://lh3.googleusercontent.com/p/AF1QipPYjh-jTdqePdlCSTDfi8WMmRyXiq_alWugBo6M=s1600-w400,https://lh3.googleusercontent.com/p/AF1QipOCilYw7X1lyXOcupyUhuC-XBH5xfvMKTF6YScr=s1600-w400,"},{"type":"Bác sỹ nha khoa","store":"Nha Khoa Chung Anh","address":"108 Ngọc Lâm, Long Biên, Hà Nội, Vietnam","location":"21.0455458,105.869583","phone":"+84 91 352 45 90","site":"...","img":"https://lh3.googleusercontent.com/p/AF1QipMvhLAP0tLzNJNrlxhPD3gi0huiOmAFTVu8agDN=s1600-w400,"},{"type":"Bác sỹ nha khoa","store":"Nha Khoa Việt Mỹ 1","address":"66 Nhân Hòa, Nhân Chính, Thanh Xuân, Hà Nội, Vietnam","location":"21.002136,105.808408","phone":"+84 98 779 28 81","site":"...","img":""},{"type":"Bác sỹ nha khoa","store":"PK Nha Khoa Kim Đồng","address":"33, 77 Ngõ 24 Kim Đồng, Giáp Bát, Hoàng Mai, Hà Nội, Vietnam","location":"20.980787,105.843662","phone":"+84 98 865 49 99","site":"...","img":""},{"type":"Bác sỹ nha khoa","store":"Nha Khoa Tiến Sỹ Lê Thanh","address":"23 Xóm Hà Hồi, Trần Hưng Đạo, Hoàn Kiếm, Hà Nội, Vietnam","location":"21.0213314,105.8473371","phone":"+84 98 965 39 02","site":"...","img":"https://lh3.googleusercontent.com/p/AF1QipOC7Fhc-0PtkFGUhwG7S5OeU3k6nMiQGGStZzzP=s1600-w400,https://lh3.googleusercontent.com/p/AF1QipOjWHiFKB7RMRZgqFCWcBlxN9smWT-ucFApnkfd=s1600-w400,https://lh3.googleusercontent.com/p/AF1QipNX9nkJpF06YYn3QsS2gabz4Kx7U2i-V5Yd7LwZ=s1600-w400,"},{"type":"Bác sỹ nha khoa","store":"Nguyen Huu Quan Dental Clinic","address":"690, Đường Trương Định, Phường Giáp Bát, Quận Hoàng Mai, Thịnh Liệt, Hoàng Mai, Hà Nội, Vietnam","location":"20.9806661,105.8452257","phone":"+84 24 6294 4368","site":"...","img":""},{"type":"Bác sỹ nha khoa","store":"NHA KHOA MOSCO","address":"Số 7 Lô A1 KĐT Đại Kim, P. Định Công, Q, Đại Kim, Hoàng Mai, Hà Nội, Vietnam","location":"20.9773757,105.8350737","phone":"+84 24 2284 8586","site":"...","img":"https://lh3.googleusercontent.com/p/AF1QipN4QJrUpwXEaDSMMfLjgxTEC3e4DE5McpB0ZLDl=s1600-w400,https://lh3.googleusercontent.com/p/AF1QipMjo2mSoUyhhtKqJ_ly5gSI89f5Zb2l84WLt0BL=s1600-w400,"},{"type":"Bác sỹ nha khoa","store":"Nha Khoa Á Châu Hoàng Mai","address":"304 Đường Hoàng Mai, Hoàng Văn Thụ, Hoàng Mai, Hà Nội, Vietnam","location":"20.9875004,105.8586791","phone":"+84 98 132 11 99","site":"...","img":""},{"type":"Bác sỹ nha khoa","store":"Nha Khoa Việt 2/390","address":"2 Ngõ 390 Nguyễn Văn Cừ, Ngọc Lâm, Long Biên, Hà Nội, Vietnam","location":"21.0454472,105.876933","phone":"+84 98 500 41 81","site":"...","img":""},{"type":"Bác sỹ nha khoa","store":"Phòng Khám Răng Hàm Mặt Bác Sĩ Lê Thị Thơm","address":"42C Lý Thường Kiệt, Tràng Tiền, Hoàn Kiếm, Hà Nội 100000, Vietnam","location":"21.0234998,105.8503935","phone":"+84 24 3824 5647","site":"...","img":""},{"type":"Bác sỹ nha khoa","store":"Le Thanh Dental Clinic","address":"23 Xóm Hà Hồi, Trần Hưng Đạo, Hoàn Kiếm, Hà Nội, Vietnam","location":"21.0210122,105.8472842","phone":"+84 98 965 39 02","site":"...","img":""},{"type":"Bác sỹ nha khoa","store":"Nha Khoa Thẩm Mỹ Hà Nội","address":"75 Lý Thường Kiệt, Cửa Nam, Hoàn Kiếm, Hà Nội, Vietnam","location":"21.0248145,105.8447919","phone":"...","site":"...","img":"https://lh3.googleusercontent.com/p/AF1QipOtwzF4OBIBtW-Z1Xr-eoNXOi0NKLqbl485HfC-=s1600-w400,"},{"type":"Bác sỹ nha khoa","store":"Nha Khoa Phạm Dương","address":"52 Bà Triệu, Trần Hưng Đạo, Hoàn Kiếm, Hà Nội, Vietnam","location":"21.0227084,105.8504917","phone":"+84 24 3824 3063","site":"http://www.nhakhoaphamduong.vn/","img":"https://lh3.googleusercontent.com/p/AF1QipOZH4w_92M2P2BXKBR9BoYEAQWrT9gvq67p-tha=s1600-w400,https://lh3.googleusercontent.com/p/AF1QipMyElo_51tXEB5s4Wwc1sRVn3oEdHdYZUXNgxLB=s1600-w400,https://lh3.googleusercontent.com/p/AF1QipPCJ4rZmYAt-SZJrD8Ijp5KhrSaXHu9r9ZnnlhR=s1600-w400,https://lh3.googleusercontent.com/p/AF1QipPJLHqPd0On3EW8ewoWuN21SEltE-eZGhgMDFmo=s1600-w400,"},{"type":"Bác sỹ nha khoa","store":"Nha khoa Tẩy trắng răng Paris Quang Trung","address":"39 Quang Trung, Tràng Tiền, Hoàn Kiếm, Hà Nội, Vietnam","location":"21.0248908,105.8497414","phone":"+84 94 377 66 99","site":"http://taytrangrang.info/","img":""},{"type":"Bác sỹ nha khoa","store":"Nha Khoa Minh Thu","address":"92 Phố Hoàng Ngân, Trung Hoà, Cầu Giấy, Hà Nội, Vietnam","location":"21.0088442,105.8077008","phone":"...","site":"...","img":""},{"type":"Bác sỹ nha khoa","store":"PHÒNG KHÁM NHA","address":"1001 Hồng Hà, Phan Chu Trinh, Hoàn Kiếm, Hà Nội, Vietnam","location":"21.0216814,105.8617715","phone":"+84 98 730 26 21","site":"https://www.nhakhoaquocteachau.vn/","img":""},{"type":"Bác sỹ nha khoa","store":"Nha Khoa Quốc Tế New.Smile","address":"15A/208 Nguyễn Văn Cừ, Ngọc Lâm, Long Biên, Hà Nội, Vietnam","location":"21.0434108,105.8732023","phone":"+84 97 737 64 10","site":"...","img":"https://lh3.googleusercontent.com/p/AF1QipOd7G8DXyfJZFVNkQnl7_oFpycAgYPUecF9QSOj=s1600-w400,https://lh3.googleusercontent.com/p/AF1QipONuZHCvNQLrMF2eTCHhfSGAhEBMJw4cRbWBcya=s1600-w400,https://lh3.googleusercontent.com/p/AF1QipOwU-NtdOli_qT_r0zCM1LfXIhq3eus4opHg-IT=s1600-w400,https://lh3.googleusercontent.com/p/AF1QipPRFsRDp02Jq7uC-8OPrIAlWYZoyUWE4ODpTQM5=s1600-w400,"},{"type":"Bác sỹ nha khoa","store":"bedental","address":"7 Tràng Thi, Tràng Tiền, Hoàn Kiếm, Hà Nội, Vietnam","location":"21.0259168,105.8510924","phone":"...","site":"...","img":""},{"type":"Bác sỹ nha khoa","store":"Ivory Dental - Nha khoa thẩm mỹ Ivory","address":"9 Nguyễn Thái Học, Cửa Nam, Hoàn Kiếm, Hà Nội, Vietnam","location":"21.02839,105.842878","phone":"+84 899 899 393","site":"https://ivorydental.vn/","img":"https://lh3.googleusercontent.com/p/AF1QipPIEKKekBJQwGZC8ZIH9sVZzm3HY3I6BgdOL_iM=s1600-w400,https://lh3.googleusercontent.com/p/AF1QipPS4-vfLuZhA9ap6oA1N4b_J-a-v9UQRH-CymVV=s1600-w400,https://lh3.googleusercontent.com/p/AF1QipMnCxyGfZzixHVmzwC9UvRNUHzatuKYzM3Cwn98=s1600-w400,https://lh3.googleusercontent.com/p/AF1QipM5fQ6FLA2_ZZxXeMfTd6CvpQOgb_W7RN-SBkE2=s1600-w400,https://lh3.googleusercontent.com/p/AF1QipPe5Unk5GADQMJZPDLc3aOeaukMXWFrGC9Cm36x=s1600-w400,https://lh3.googleusercontent.com/p/AF1QipOSoFRhw5RIQDnwMtF9RqozNa0LvUznK_IWPVFQ=s1600-w400,https://lh3.googleusercontent.com/p/AF1QipMxIvr7Xwdhy4-Jvt2S5Whq2tTC5E4xaGGhviFc=s1600-w400,https://lh3.googleusercontent.com/p/AF1QipOxwISB1dqPi7Mnt1MAE401kgkH1OJweeeT_J4V=s1600-w400,https://lh3.googleusercontent.com/p/AF1QipPibCzUVBNyYxm7my5TiBzwAufxv1gcSb2_ijfU=s1600-w400,https://lh3.googleusercontent.com/p/AF1QipOyXUKoG_NndKGs8jCzDhD1Wi9wPmgYUOa_B2_e=s1600-w400,"},{"type":"Bác sỹ nha khoa","store":"Phòng Khám Răng Hàm Mặt Phan Xuân Tân","address":"345-C6, Tân Mai, Phường Tân Mai, Quận Hoàng Mai, Thành Phố Hà Nội, Tân Mai, Hoàng Mai, Hà Nội, Vietnam","location":"20.9833592,105.8489585","phone":"+84 24 3864 6817","site":"...","img":""},{"type":"Bác sỹ nha khoa","store":"Nha Khoa Laser 108","address":"2, Trần Hưng Đạo, Phường Cửa Nam, Quận Hoàn Kiếm, Cửa Nam, Hoàn Kiếm, Hà Nội, Vietnam","location":"21.0238238,105.8434331","phone":"+84 24 2247 2286","site":"...","img":""},{"type":"Bác sỹ nha khoa","store":"Sun Dental Care","address":"1 Ngõ Dã Tượng, Trần Hưng Đạo, Hoàn Kiếm, Hà Nội, Vietnam","location":"21.0234376,105.8467168","phone":"+84 91 225 22 55","site":"...","img":"https://lh3.googleusercontent.com/p/AF1QipMENk2aXyG4_BhToYPHb_U9y3PW0m1jZelJ3_xz=s1600-w400,https://lh3.googleusercontent.com/p/AF1QipPJPoY_vjU0h-qvg7idOPxe_vBtlfFvwHWCqWLb=s1600-w400,https://lh3.googleusercontent.com/p/AF1QipOFhI9VSc6EVppilM_KkuI-GchGDnKj2s0Qa_DN=s1600-w400,https://lh3.googleusercontent.com/p/AF1QipNAyMrvXSmoUEeJpMBG2pcNyw3cBcJQHIR6mjts=s1600-w400,https://lh3.googleusercontent.com/p/AF1QipN_jAWSLKXIqfuYvb-67KrPOWiKIKOJsgQWU2fi=s1600-w400,https://lh3.googleusercontent.com/p/AF1QipMqeLhZ_E3hpAjmM37TzvzWoydNt4Gx_Qi5h2Pk=s1600-w400,"},{"type":"Bác sỹ nha khoa","store":"Nha khoa Mỹ","address":"11 Cửa Nam, Hoàn Kiếm, Hà Nội, Vietnam","location":"21.028034,105.843949","phone":"+84 1800 8005","site":"...","img":""},{"type":"Bác sỹ nha khoa","store":"Sakura Dentistry","address":"54 Đường Lê Duẩn, Văn Miếu, Hoàn Kiếm, Hà Nội, Vietnam","location":"21.0274947,105.8414114","phone":"+84 98 935 53 33","site":"...","img":"https://lh3.googleusercontent.com/p/AF1QipN7leE0rpffXokERIN8oD9beZtcoOHvg9paj-D4=s1600-w400,https://lh3.googleusercontent.com/p/AF1QipOZAZoWQ7Yz2ahNfAlzk9TEIzTgi-mXq4BTjM7P=s1600-w400,https://lh3.googleusercontent.com/p/AF1QipPZ-FxSYTqY-568SLSpSO1Ejh2KzA5m-skAZ9Pt=s1600-w400,https://lh3.googleusercontent.com/p/AF1QipMBICOWGMXOZ8IpxsZfLkwJtJ4LHZwxy5_RI7Fu=s1600-w400,https://lh3.googleusercontent.com/p/AF1QipMMUbxTXiYaOzKji0E-ILaPrpZms-vnPb7Btki4=s1600-w400,https://lh3.googleusercontent.com/p/AF1QipPZaAxl0fmz6m7SyKR6ue7jqjwhN6i0c__4DHhi=s1600-w400,https://lh3.googleusercontent.com/p/AF1QipNghpcPsGX_3gpWIQdNAUrUnOqKAjR9_cdOduG1=s1600-w400,"},{"type":"Bác sỹ nha khoa","store":"Dược Mỹ Phẩm MP1","address":"51B Đường Lê Duẩn, Văn Miếu, Hoàn Kiếm, Hà Nội, Vietnam","location":"21.0266386,105.8415964","phone":"+84 384 823 075","site":"...","img":""},{"type":"Bác sỹ nha khoa","store":"Nha Khoa Apple","address":"77 a Thợ Nhuộm, Trần Hưng Đạo, Hoàn Kiếm, Hà Nội, Vietnam","location":"21.023662,105.847797","phone":"+84 91 303 52 73","site":"...","img":"https://lh3.googleusercontent.com/p/AF1QipMb0fY8kpg2N4VOpLxmcTSvEIZbClyO1h1VAZD8=s1600-w400,"},{"type":"Bác sỹ nha khoa","store":"Dental Clinic","address":"67 Nam Ngư, Cửa Nam, Hoàn Kiếm, Hà Nội, Vietnam","location":"21.0264871,105.8418583","phone":"+84 24 3941 0463","site":"...","img":""},{"type":"Bác sỹ nha khoa","store":"LIEN THANH DENTAL CLINIC","address":"30a Xóm Hà Hồi, Trần Hưng Đạo, Hoàn Kiếm, Hà Nội, Vietnam","location":"21.021521,105.846991","phone":"+84 24 6267 6767","site":"http://www.nhakhoalienthanh.com.vn/","img":"https://lh3.googleusercontent.com/p/AF1QipP-0foEnBvA2fZe_jYtCqCkLegXwlwYuy1sVhCL=s1600-w400,https://lh3.googleusercontent.com/p/AF1QipNSapBudjbhWPtrAmNpRj_heYyUUYFBVM2bdJYi=s1600-w400,https://lh3.googleusercontent.com/p/AF1QipPJ3lA2sKl_S4bDa2fkb-r1BYPvL9EOtB4aZiRA=s1600-w400,https://lh3.googleusercontent.com/p/AF1QipNMd2-mRUFHgRwaxOqBhW4e2_IM2H0OvUhCZCos=s1600-w400,"},{"type":"Bác sỹ nha khoa","store":"Nha khoa Toàn Tâm","address":"61 Nguyễn Quý Đức, Thanh Xuân Bắc, Thanh Xuân, Hà Nội, Vietnam","location":"20.9930017,105.7970155","phone":"...","site":"https://www.facebook.com/nhakhoatoantamtot","img":""},{"type":"Bác sỹ nha khoa","store":"Phòng Khám Nha Khoa Tư Nhân Minh Sinh","address":"46C Quán Sứ, Hàng Bông, Hoàn Kiếm, Hà Nội, Vietnam","location":"21.0282147,105.8460713","phone":"...","site":"...","img":""},{"type":"Bác sỹ nha khoa","store":"PHÒNG KHÁM NHA KHOA RĂNG XINH","address":"126 Phố Tân Mai, Tân Mai, Hoàng Mai, Hà Nội, Vietnam","location":"20.983624,105.849442","phone":"+84 90 438 19 93","site":"...","img":""},{"type":"Bác sỹ nha khoa","store":"Nha khoa Paris","address":"39 Quang Trung, Trần Hưng Đạo, Hoàn Kiếm, Hà Nội, Vietnam","location":"21.0200126,105.8480995","phone":"...","site":"...","img":""},{"type":"Bác sỹ nha khoa","store":"Phòng Khám Răng Hàm Mặt","address":"75 Tràng Thi, Hàng Bông, Hoàn Kiếm, Hà Nội, Vietnam","location":"21.027953,105.844422","phone":"+84 98 730 26 21","site":"...","img":"https://lh3.googleusercontent.com/p/AF1QipMfg6R6vPEQxDu9QPDC65tTO2FXm9EOfuoabLoZ=s1600-w385,"},{"type":"Bác sỹ nha khoa","store":"Nha Khoa Việt Đức","address":"84A Hai Bà Trưng, Cửa Nam, Hoàn Kiếm, Hà Nội, Vietnam","location":"21.02688,105.8443443","phone":"+84 24 3936 9777","site":"http://www.nhakhoavietduc.com.vn/","img":"https://lh3.googleusercontent.com/p/AF1QipMCzb333OInFaNCZOG4w6jPoJh3EZmUKDWPabFs=s1600-w400,https://lh3.googleusercontent.com/p/AF1QipMcl3E1VyAGF_OA0n9gloxZeKlRz_71XaDupane=s1600-w400,"},{"type":"Bác sỹ nha khoa","store":"Nha khoa CNB Dental Home","address":"20 P. Ngô Quyền, Tràng Tiền, Hoàn Kiếm, Hà Nội, Vietnam","location":"21.0243782,105.8547734","phone":"+84 97 512 31 89","site":"...","img":"https://lh3.googleusercontent.com/p/AF1QipN6wX-OnCgTd-f8ZQPeoE4Z70V4-Gdtwg1B5hHW=s1600-w400,https://lh3.googleusercontent.com/p/AF1QipOq2nSE1Qhvp1axjLjF7BPOOzw0Ww6uwk70Jvbg=s1600-w400,https://lh3.googleusercontent.com/p/AF1QipMDwFrw7Dbzmo99tIeR_0zF4kwLbQrX-72jfz2S=s1600-w400,https://lh3.googleusercontent.com/p/AF1QipOtiWUdR07s4Lbjninrny9JZfTR3p6wCVOc42nM=s1600-w400,https://lh3.googleusercontent.com/p/AF1QipPQA7jjf5bGl3dGMkFx0PThEfl3C3geSIvgWxr-=s1600-w400,https://lh3.googleusercontent.com/p/AF1QipMh60ZpNmgrb5ZmKGbuJ20U7sjJ33gwUrlSvzFY=s1600-w400,https://lh3.googleusercontent.com/p/AF1QipOcbi3E6QYMEGi8QeoWQ9UAEmFmghxbND14u1Be=s1600-w400,https://lh3.googleusercontent.com/p/AF1QipMwM606bxvVlGCD8_ns6B0Nf61w6Kb9NHyrbByL=s1600-w400,https://lh3.googleusercontent.com/p/AF1QipPSUDdtPKsca0YCHz-2RK3LHXpUedDIgleaueO3=s1600-w400,https://lh3.googleusercontent.com/p/AF1QipOdUDOdU5H2fy7Q7hjxq8UPfTSoPExlHM7zFBm5=s1600-w400,"},{"type":"Bác sỹ nha khoa","store":"Nha khoa Paris","address":"39 Quang Trung, Trần Hưng Đạo, Hoàn Kiếm, Hà Nội, Vietnam","location":"21.0199889,105.8481044","phone":"...","site":"...","img":""},{"type":"Bác sỹ nha khoa","store":"Thúy Phương Dentist - Nha Khoa Thẩm Mỹ","address":"4C P. Tôn Đức Thắng, Cát Linh, Đống Đa, Hà Nội, Vietnam","location":"21.0300315,105.8356449","phone":"+84 96 231 31 61","site":"https://thuyphuongdentist.com/","img":""},{"type":"Bác sỹ nha khoa","store":"Nha Khoa Huy Hoàng","address":"25 Ngô Sĩ Liên, Văn Miếu, Hà Đông, Hà Nội, Vietnam","location":"21.0273175,105.8389099","phone":"+84 96 300 54 48","site":"...","img":""},{"type":"Bác sỹ nha khoa","store":"Phòng Khám Chuyên Khoa Răng Hàm Mặt - Bs Nguyễn Văn Dĩ","address":"23A Hội Vũ, Hàng Bông, Hoàn Kiếm, Hà Nội 10000, Vietnam","location":"21.028363,105.8451245","phone":"+84 91 352 23 23","site":"...","img":""},{"type":"Bác sỹ nha khoa","store":"Dentistry Paris Hanoi","address":"39 Quang Trung, Trần Hưng Đạo, Hoàn Kiếm, Hà Nội 111006, Vietnam","location":"21.0199889,105.8481044","phone":"+84 94 377 66 99","site":"http://nhakhoaparis.vn/","img":"https://lh3.googleusercontent.com/p/AF1QipM_nPGbNX4a8Elpr_6b1inSftJf94FXh-Mr5MEW=s1600-w400,https://lh3.googleusercontent.com/p/AF1QipNZh0EHiXfu6Imj0IHyoN9BaUYYKICc-U1gpUfX=s1600-w400,https://lh3.googleusercontent.com/p/AF1QipNZRy1OUnMyCrYYrqN59OtpR2VY7oK2tsBfKNgO=s1600-w400,https://lh3.googleusercontent.com/p/AF1QipNMuxWNXvFFQ1QzHpMh0nDA5m-1zrbYo7ODNKkb=s1600-w400,https://lh3.googleusercontent.com/p/AF1QipM4GBmGBRtVqUXqLTn-pze1_zpEWWClBJBZc6YE=s1600-w400,https://lh3.googleusercontent.com/p/AF1QipPiOyBaSu0TjVKH7dzqdI76ihV6Vbx1v02fwz7J=s1600-w400,https://lh3.googleusercontent.com/p/AF1QipOBj9DKLIy85BhtHvi8HRoSY6R6Kg2v6gYZiTpp=s1600-w400,https://lh3.googleusercontent.com/p/AF1QipP5KL1mU-iuDF-yLaFGxVkyrZoPOTo_CkK_Ck5v=s1600-w400,https://lh3.googleusercontent.com/p/AF1QipMZuEHhA4MJrTVlH3fCFCVoSWaLNBdfCSYm-OO6=s1600-w400,https://lh3.googleusercontent.com/p/AF1QipNt31w2PdS_tkSGe0vR_ft9ySE3for-ki4X6pcq=s1600-w400,"},{"type":"Bác sỹ nha khoa","store":"MInh Thu Dental","address":"92 Phố Hoàng Ngân, Trung Hoà, Cầu Giấy, Hà Nội, Vietnam","location":"21.0088442,105.8077008","phone":"...","site":"...","img":""},{"type":"Bác sỹ nha khoa","store":"Nha Khoa Minh Huệ","address":"60 Đường Lê Duẩn, Văn Miếu, Đống Đa, Hà Nội, Vietnam","location":"21.0273789,105.8416146","phone":"+84 91 541 93 40","site":"...","img":"https://lh3.googleusercontent.com/p/AF1QipMXMv85AzUITwc1xXwIKA7Gm5IcBvzDqBY7O-r9=s1600-w400,"},{"type":"Bác sỹ nha khoa","store":"Nha Khoa Thanh Phương","address":"148 Phố Nguyễn Khuyến, Văn Miếu, Đống Đa, Hà Nội, Vietnam","location":"21.0286407,105.8366793","phone":"+84 24 3747 3798","site":"http://nhakhoathanhphuong.com.vn/32/nghien-rang-ban-dem.html","img":"https://lh3.googleusercontent.com/p/AF1QipPAK-8Bot_lsqWghkdXfbS0jfPCtYeZpurxh1PI=s1600-w400,https://lh3.googleusercontent.com/p/AF1QipNGmVt9j1Qz5THgFOJXLpUDUybom91zKv0Rhcbc=s1600-w400,https://lh3.googleusercontent.com/p/AF1QipMNil50zlvFAYA9VmpIlBRbKt_-RIY1lTFJ7jkJ=s1600-w400,"},{"type":"Bác sỹ nha khoa","store":"Nha Khoa Lê Nguyên","address":"21 Long Biên 2, Ngọc Lâm, Long Biên, Hà Nội 100000, Vietnam","location":"21.0450056,105.867675","phone":"+84 98 845 55 66","site":"...","img":""},{"type":"Bác sỹ nha khoa","store":"Vietnam Germany International Dental Unit 1","address":"84 Hai Bà Trưng, Trần Hưng Đạo, Hoàn Kiếm, Hà Nội, Vietnam","location":"21.0269696,105.8443764","phone":"+84 1900 6465","site":"http://nhakhoavietduc.com.vn/","img":"https://lh3.googleusercontent.com/p/AF1QipPcbTvbJrtTf6OcPI4IGX70hZWtntNUWdyW8Kgm=s1600-w400,https://lh3.googleusercontent.com/p/AF1QipN5lqjcPwhw0y0x98F63akp1dp3WvJ-iMD_kngB=s1600-w400,https://lh3.googleusercontent.com/p/AF1QipOQ6rHMPG3R5WtaxN-4HiQNdROZwmOypnwI8AyO=s1600-w400,https://lh3.googleusercontent.com/p/AF1QipOqiC2F9wPaE2Kp-ZN-M2dVOMfuaDvTby88Tl6B=s1600-w400,https://lh3.googleusercontent.com/p/AF1QipNT_KeWsKYIEj5QPQ1SfgO_tGmWg07BVWDQcsjM=s1600-w400,https://lh3.googleusercontent.com/p/AF1QipMycTgI-tnrloquEMpC5z26dUhao1bF8ToLuUQn=s1600-w400,https://lh3.googleusercontent.com/p/AF1QipNp1L8DmsK2mk59MK6Ce3cLxaS97lPJz9L2gpe4=s1600-w320,https://lh3.googleusercontent.com/p/AF1QipP-ZH0SOWVg1cN6ge7Vfn65DZJPIH-lz0aF5wn1=s1600-w400,https://lh3.googleusercontent.com/p/AF1QipOeNGZF8NIoGzZu61P-x_eDkBjJ9jqgz7LSNg5W=s1600-w400,https://lh3.googleusercontent.com/p/AF1QipNyCvVGbHt1n12vt9PKfaSh6djFC3ThitLEfSSZ=s1600-w400,"},{"type":"Bác sỹ nha khoa","store":"Phòng Khám Răng Hàm Mặt Minh Sinh","address":"46C Quán Sứ, Hàng Bông, Hoàn Kiếm, Hà Nội 100000, Vietnam","location":"21.0282097,105.8460995","phone":"+84 24 3826 7778","site":"...","img":"https://lh3.googleusercontent.com/p/AF1QipN8jsH4mmh5G-FRMlVc5gk4tasvx2xjVkiL4L3m=s1600-w400,"},{"type":"Bác sỹ nha khoa","store":"Nha Khoa Trẻ","address":"38 Ngụy Như Kon Tum, Nhân Chính, Thanh Xuân, Hà Nội, Vietnam","location":"20.9983391,105.7997414","phone":"+84 96 333 38 44","site":"https://nhakhoatre.business.site/?utm_source=gmb&utm_medium=ref","img":"https://lh3.googleusercontent.com/p/AF1QipO0HJfo-3PjxcKZa7IZ5Mc-WUyHLBTOhK51m2xq=s1600-w400,https://lh3.googleusercontent.com/p/AF1QipMcuTtzBWXIhHNzT4yTzACXX1wlXe5YWJT9uT67=s1600-w400,https://lh3.googleusercontent.com/p/AF1QipP2qs7ZrqyJ_CR6N7D5krcHD4tCOmwnr70Sr2OL=s1600-w400,https://lh3.googleusercontent.com/p/AF1QipN3R8BjFJOYN2ADwWZoII8Wzl5Qg7jrDvy1aYft=s1600-w400,https://lh3.googleusercontent.com/p/AF1QipMHT13kq5w_8MmMeSpUDfzboIvz1pwvtjweJiy2=s1600-w400,https://lh3.googleusercontent.com/p/AF1QipOn1zMk792Em5TrvqzYbVpUIl3mhVFUOqhk3ipt=s1600-w400,https://lh3.googleusercontent.com/p/AF1QipMaokSP7b7DWGVOIQAR95b5ls2aTY43iUMSksYt=s1600-w400,https://lh3.googleusercontent.com/p/AF1QipPOGwSYnT31xADc9RNUkrWc20yE03G8V94p5PBw=s1600-w400,https://lh3.googleusercontent.com/p/AF1QipOGuZJ_1cH1Hlahw495IXfF3_ysI6RLeLitErIU=s1600-w400,https://lh3.googleusercontent.com/p/AF1QipMnscHGMilpzDQ2Ol1Ezw9_pTGlbM_aaEN0Ix_8=s1600-w400,"},{"type":"Bác sỹ nha khoa","store":"Nha Khoa Văn Minh","address":"49 Nguyễn Như Đổ, Văn Miếu, Đống Đa, Hà Nội, Vietnam","location":"21.026663,105.8386137","phone":"...","site":"...","img":"https://lh3.googleusercontent.com/p/AF1QipOjfh8f4DKZeSP2RYU4WVwKT8SVh9DOgqqiaF2e=s1600-w400,https://lh3.googleusercontent.com/p/AF1QipPpOyBsDfkN3XXWDH6nMYUgsc5afGipPyqxkjRg=s1600-w400,"},{"type":"Bác sỹ nha khoa","store":"Phòng Khám Bệnh Tư Nhân Răng Hàm Mặt Minh Huệ","address":"60B Đường Lê Duẩn, Văn Miếu, Hoàn Kiếm, Hà Nội, Vietnam","location":"21.0273041,105.8418135","phone":"+84 91 541 93 40","site":"...","img":""},{"type":"Bác sỹ nha khoa","store":"Phòng Khám Nha Khoa Thẩm Mỹ Thủ Đô","address":"2A Trần Hưng Đạo, Phan Chu Trinh, Hoàn Kiếm, Hà Nội, Vietnam","location":"21.0188411,105.8605911","phone":"+84 98 331 50 07","site":"...","img":""},{"type":"Bác sỹ nha khoa","store":"Nha Khoa Minh Tâm","address":"2 Trần Hưng Đạo, Phan Chu Trinh, Hoàn Kiếm, Hà Nội, Vietnam","location":"21.0194524,105.8610259","phone":"...","site":"...","img":""},{"type":"Bác sỹ nha khoa","store":"Phòng Khám Răng Phạm Ngọc Hồ","address":"40, Đường Ấu Triệu, Hàng Trống, Hoàn Kiếm, Hà Nội, Vietnam","location":"21.0286802,105.8483895","phone":"+84 24 3828 6006","site":"...","img":"https://lh3.googleusercontent.com/p/AF1QipNyaFYX7rS1UWJWaKx9XwqIK19ofMx4ZyxjuOZx=s1600-w400,"}]